sequential_circuits/registers/siso_register.v
module siso_register(so, clk, rst, si);
    input si, clk, rst;
    output so;
    reg [7:0] sr;
    always @(negedge clk) begin
        if (rst) sr <= 8'b0;
        else sr <= {si, sr[7:1]};
    end
    assign so = sr[0];
endmodule

sequential_circuits/registers/siso_register_tb.v
`timescale 1ps/1ps
`include "siso_register.v"

module siso_register_tb;
    reg si, clk, rst;
    wire so;
    integer i, k;
    integer j = 32'b 1100_0110_1110_1111_0001_0101_1010_1101;
    siso_register sisor1(so, clk, rst, si);
    initial begin
        clk = 0;
        $dumpfile("siso_register_tb.vcd");
        $dumpvars;
        for (i = 0; i < 1000; i = i+1) begin
            #10 clk <= ~clk;
        end
    end
    initial begin
        rst = 0;
        for (k = 0; k < 32; k = k+1)begin
            #20 si <= j[k];
        end
    end
endmodule

sequential_circuits/registers/siso_register_tb.vcd
$date
	Fri Dec 22 15:29:01 2023
$end
$version
	Icarus Verilog
$end
$timescale
	1ps
$end
$scope module siso_register_tb $end
$var wire 1 ! so $end
$var reg 1 " clk $end
$var reg 1 # rst $end
$var reg 1 $ si $end
$var integer 32 % i [31:0] $end
$var integer 32 & j [31:0] $end
$var integer 32 ' k [31:0] $end
$scope module sisor1 $end
$var wire 1 " clk $end
$var wire 1 # rst $end
$var wire 1 $ si $end
$var wire 1 ! so $end
$var reg 8 ( sr [7:0] $end
$upscope $end
$upscope $end
$enddefinitions $end
$comment Show the parameter values. $end
$dumpall
$end
#0
$dumpvars
bx (
b0 '
b11000110111011110001010110101101 &
b0 %
x$
0#
0"
x!
$end
#10
1"
b1 %
#20
b1xxxxxxx (
0"
1$
b10 %
b1 '
#30
1"
b11 %
#40
b1xxxxxx (
0"
0$
b100 %
b10 '
#50
1"
b101 %
#60
b101xxxxx (
0"
1$
b110 %
b11 '
#70
1"
b111 %
#80
b1101xxxx (
0"
b1000 %
b100 '
#90
1"
b1001 %
#100
b1101xxx (
0"
0$
b1010 %
b101 '
#110
1"
b1011 %
#120
b101101xx (
0"
1$
b1100 %
b110 '
#130
1"
b1101 %
#140
b101101x (
0"
0$
b1110 %
b111 '
#150
1"
b1111 %
#160
1!
b10101101 (
0"
1$
b10000 %
b1000 '
#170
1"
b10001 %
#180
0!
b11010110 (
0"
b10010 %
b1001 '
#190
1"
b10011 %
#200
1!
b1101011 (
0"
0$
b10100 %
b1010 '
#210
1"
b10101 %
#220
b10110101 (
0"
1$
b10110 %
b1011 '
#230
1"
b10111 %
#240
0!
b1011010 (
0"
0$
b11000 %
b1100 '
#250
1"
b11001 %
#260
1!
b10101101 (
0"
1$
b11010 %
b1101 '
#270
1"
b11011 %
#280
0!
b1010110 (
0"
0$
b11100 %
b1110 '
#290
1"
b11101 %
#300
1!
b101011 (
0"
b11110 %
b1111 '
#310
1"
b11111 %
#320
b10101 (
0"
b100000 %
b10000 '
#330
1"
b100001 %
#340
0!
b10001010 (
0"
1$
b100010 %
b10001 '
#350
1"
b100011 %
#360
1!
b11000101 (
0"
b100100 %
b10010 '
#370
1"
b100101 %
#380
0!
b11100010 (
0"
b100110 %
b10011 '
#390
1"
b100111 %
#400
1!
b11110001 (
0"
b101000 %
b10100 '
#410
1"
b101001 %
#420
0!
b1111000 (
0"
0$
b101010 %
b10101 '
#430
1"
b101011 %
#440
b10111100 (
0"
1$
b101100 %
b10110 '
#450
1"
b101101 %
#460
b11011110 (
0"
b101110 %
b10111 '
#470
1"
b101111 %
#480
1!
b11101111 (
0"
b110000 %
b11000 '
#490
1"
b110001 %
#500
b1110111 (
0"
0$
b110010 %
b11001 '
#510
1"
b110011 %
#520
b10111011 (
0"
1$
b110100 %
b11010 '
#530
1"
b110101 %
#540
b11011101 (
0"
b110110 %
b11011 '
#550
1"
b110111 %
#560
0!
b1101110 (
0"
0$
b111000 %
b11100 '
#570
1"
b111001 %
#580
1!
b110111 (
0"
b111010 %
b11101 '
#590
1"
b111011 %
#600
b11011 (
0"
b111100 %
b11110 '
#610
1"
b111101 %
#620
b10001101 (
0"
1$
b111110 %
b11111 '
#630
1"
b111111 %
#640
0!
b11000110 (
0"
b1000000 %
b100000 '
#650
1"
b1000001 %
#660
1!
b11100011 (
0"
b1000010 %
#670
1"
b1000011 %
#680
b11110001 (
0"
b1000100 %
#690
1"
b1000101 %
#700
0!
b11111000 (
0"
b1000110 %
#710
1"
b1000111 %
#720
b11111100 (
0"
b1001000 %
#730
1"
b1001001 %
#740
b11111110 (
0"
b1001010 %
#750
1"
b1001011 %
#760
1!
b11111111 (
0"
b1001100 %
#770
1"
b1001101 %
#780
0"
b1001110 %
#790
1"
b1001111 %
#800
0"
b1010000 %
#810
1"
b1010001 %
#820
0"
b1010010 %
#830
1"
b1010011 %
#840
0"
b1010100 %
#850
1"
b1010101 %
#860
0"
b1010110 %
#870
1"
b1010111 %
#880
0"
b1011000 %
#890
1"
b1011001 %
#900
0"
b1011010 %
#910
1"
b1011011 %
#920
0"
b1011100 %
#930
1"
b1011101 %
#940
0"
b1011110 %
#950
1"
b1011111 %
#960
0"
b1100000 %
#970
1"
b1100001 %
#980
0"
b1100010 %
#990
1"
b1100011 %
#1000
0"
b1100100 %
#1010
1"
b1100101 %
#1020
0"
b1100110 %
#1030
1"
b1100111 %
#1040
0"
b1101000 %
#1050
1"
b1101001 %
#1060
0"
b1101010 %
#1070
1"
b1101011 %
#1080
0"
b1101100 %
#1090
1"
b1101101 %
#1100
0"
b1101110 %
#1110
1"
b1101111 %
#1120
0"
b1110000 %
#1130
1"
b1110001 %
#1140
0"
b1110010 %
#1150
1"
b1110011 %
#1160
0"
b1110100 %
#1170
1"
b1110101 %
#1180
0"
b1110110 %
#1190
1"
b1110111 %
#1200
0"
b1111000 %
#1210
1"
b1111001 %
#1220
0"
b1111010 %
#1230
1"
b1111011 %
#1240
0"
b1111100 %
#1250
1"
b1111101 %
#1260
0"
b1111110 %
#1270
1"
b1111111 %
#1280
0"
b10000000 %
#1290
1"
b10000001 %
#1300
0"
b10000010 %
#1310
1"
b10000011 %
#1320
0"
b10000100 %
#1330
1"
b10000101 %
#1340
0"
b10000110 %
#1350
1"
b10000111 %
#1360
0"
b10001000 %
#1370
1"
b10001001 %
#1380
0"
b10001010 %
#1390
1"
b10001011 %
#1400
0"
b10001100 %
#1410
1"
b10001101 %
#1420
0"
b10001110 %
#1430
1"
b10001111 %
#1440
0"
b10010000 %
#1450
1"
b10010001 %
#1460
0"
b10010010 %
#1470
1"
b10010011 %
#1480
0"
b10010100 %
#1490
1"
b10010101 %
#1500
0"
b10010110 %
#1510
1"
b10010111 %
#1520
0"
b10011000 %
#1530
1"
b10011001 %
#1540
0"
b10011010 %
#1550
1"
b10011011 %
#1560
0"
b10011100 %
#1570
1"
b10011101 %
#1580
0"
b10011110 %
#1590
1"
b10011111 %
#1600
0"
b10100000 %
#1610
1"
b10100001 %
#1620
0"
b10100010 %
#1630
1"
b10100011 %
#1640
0"
b10100100 %
#1650
1"
b10100101 %
#1660
0"
b10100110 %
#1670
1"
b10100111 %
#1680
0"
b10101000 %
#1690
1"
b10101001 %
#1700
0"
b10101010 %
#1710
1"
b10101011 %
#1720
0"
b10101100 %
#1730
1"
b10101101 %
#1740
0"
b10101110 %
#1750
1"
b10101111 %
#1760
0"
b10110000 %
#1770
1"
b10110001 %
#1780
0"
b10110010 %
#1790
1"
b10110011 %
#1800
0"
b10110100 %
#1810
1"
b10110101 %
#1820
0"
b10110110 %
#1830
1"
b10110111 %
#1840
0"
b10111000 %
#1850
1"
b10111001 %
#1860
0"
b10111010 %
#1870
1"
b10111011 %
#1880
0"
b10111100 %
#1890
1"
b10111101 %
#1900
0"
b10111110 %
#1910
1"
b10111111 %
#1920
0"
b11000000 %
#1930
1"
b11000001 %
#1940
0"
b11000010 %
#1950
1"
b11000011 %
#1960
0"
b11000100 %
#1970
1"
b11000101 %
#1980
0"
b11000110 %
#1990
1"
b11000111 %
#2000
0"
b11001000 %
#2010
1"
b11001001 %
#2020
0"
b11001010 %
#2030
1"
b11001011 %
#2040
0"
b11001100 %
#2050
1"
b11001101 %
#2060
0"
b11001110 %
#2070
1"
b11001111 %
#2080
0"
b11010000 %
#2090
1"
b11010001 %
#2100
0"
b11010010 %
#2110
1"
b11010011 %
#2120
0"
b11010100 %
#2130
1"
b11010101 %
#2140
0"
b11010110 %
#2150
1"
b11010111 %
#2160
0"
b11011000 %
#2170
1"
b11011001 %
#2180
0"
b11011010 %
#2190
1"
b11011011 %
#2200
0"
b11011100 %
#2210
1"
b11011101 %
#2220
0"
b11011110 %
#2230
1"
b11011111 %
#2240
0"
b11100000 %
#2250
1"
b11100001 %
#2260
0"
b11100010 %
#2270
1"
b11100011 %
#2280
0"
b11100100 %
#2290
1"
b11100101 %
#2300
0"
b11100110 %
#2310
1"
b11100111 %
#2320
0"
b11101000 %
#2330
1"
b11101001 %
#2340
0"
b11101010 %
#2350
1"
b11101011 %
#2360
0"
b11101100 %
#2370
1"
b11101101 %
#2380
0"
b11101110 %
#2390
1"
b11101111 %
#2400
0"
b11110000 %
#2410
1"
b11110001 %
#2420
0"
b11110010 %
#2430
1"
b11110011 %
#2440
0"
b11110100 %
#2450
1"
b11110101 %
#2460
0"
b11110110 %
#2470
1"
b11110111 %
#2480
0"
b11111000 %
#2490
1"
b11111001 %
#2500
0"
b11111010 %
#2510
1"
b11111011 %
#2520
0"
b11111100 %
#2530
1"
b11111101 %
#2540
0"
b11111110 %
#2550
1"
b11111111 %
#2560
0"
b100000000 %
#2570
1"
b100000001 %
#2580
0"
b100000010 %
#2590
1"
b100000011 %
#2600
0"
b100000100 %
#2610
1"
b100000101 %
#2620
0"
b100000110 %
#2630
1"
b100000111 %
#2640
0"
b100001000 %
#2650
1"
b100001001 %
#2660
0"
b100001010 %
#2670
1"
b100001011 %
#2680
0"
b100001100 %
#2690
1"
b100001101 %
#2700
0"
b100001110 %
#2710
1"
b100001111 %
#2720
0"
b100010000 %
#2730
1"
b100010001 %
#2740
0"
b100010010 %
#2750
1"
b100010011 %
#2760
0"
b100010100 %
#2770
1"
b100010101 %
#2780
0"
b100010110 %
#2790
1"
b100010111 %
#2800
0"
b100011000 %
#2810
1"
b100011001 %
#2820
0"
b100011010 %
#2830
1"
b100011011 %
#2840
0"
b100011100 %
#2850
1"
b100011101 %
#2860
0"
b100011110 %
#2870
1"
b100011111 %
#2880
0"
b100100000 %
#2890
1"
b100100001 %
#2900
0"
b100100010 %
#2910
1"
b100100011 %
#2920
0"
b100100100 %
#2930
1"
b100100101 %
#2940
0"
b100100110 %
#2950
1"
b100100111 %
#2960
0"
b100101000 %
#2970
1"
b100101001 %
#2980
0"
b100101010 %
#2990
1"
b100101011 %
#3000
0"
b100101100 %
#3010
1"
b100101101 %
#3020
0"
b100101110 %
#3030
1"
b100101111 %
#3040
0"
b100110000 %
#3050
1"
b100110001 %
#3060
0"
b100110010 %
#3070
1"
b100110011 %
#3080
0"
b100110100 %
#3090
1"
b100110101 %
#3100
0"
b100110110 %
#3110
1"
b100110111 %
#3120
0"
b100111000 %
#3130
1"
b100111001 %
#3140
0"
b100111010 %
#3150
1"
b100111011 %
#3160
0"
b100111100 %
#3170
1"
b100111101 %
#3180
0"
b100111110 %
#3190
1"
b100111111 %
#3200
0"
b101000000 %
#3210
1"
b101000001 %
#3220
0"
b101000010 %
#3230
1"
b101000011 %
#3240
0"
b101000100 %
#3250
1"
b101000101 %
#3260
0"
b101000110 %
#3270
1"
b101000111 %
#3280
0"
b101001000 %
#3290
1"
b101001001 %
#3300
0"
b101001010 %
#3310
1"
b101001011 %
#3320
0"
b101001100 %
#3330
1"
b101001101 %
#3340
0"
b101001110 %
#3350
1"
b101001111 %
#3360
0"
b101010000 %
#3370
1"
b101010001 %
#3380
0"
b101010010 %
#3390
1"
b101010011 %
#3400
0"
b101010100 %
#3410
1"
b101010101 %
#3420
0"
b101010110 %
#3430
1"
b101010111 %
#3440
0"
b101011000 %
#3450
1"
b101011001 %
#3460
0"
b101011010 %
#3470
1"
b101011011 %
#3480
0"
b101011100 %
#3490
1"
b101011101 %
#3500
0"
b101011110 %
#3510
1"
b101011111 %
#3520
0"
b101100000 %
#3530
1"
b101100001 %
#3540
0"
b101100010 %
#3550
1"
b101100011 %
#3560
0"
b101100100 %
#3570
1"
b101100101 %
#3580
0"
b101100110 %
#3590
1"
b101100111 %
#3600
0"
b101101000 %
#3610
1"
b101101001 %
#3620
0"
b101101010 %
#3630
1"
b101101011 %
#3640
0"
b101101100 %
#3650
1"
b101101101 %
#3660
0"
b101101110 %
#3670
1"
b101101111 %
#3680
0"
b101110000 %
#3690
1"
b101110001 %
#3700
0"
b101110010 %
#3710
1"
b101110011 %
#3720
0"
b101110100 %
#3730
1"
b101110101 %
#3740
0"
b101110110 %
#3750
1"
b101110111 %
#3760
0"
b101111000 %
#3770
1"
b101111001 %
#3780
0"
b101111010 %
#3790
1"
b101111011 %
#3800
0"
b101111100 %
#3810
1"
b101111101 %
#3820
0"
b101111110 %
#3830
1"
b101111111 %
#3840
0"
b110000000 %
#3850
1"
b110000001 %
#3860
0"
b110000010 %
#3870
1"
b110000011 %
#3880
0"
b110000100 %
#3890
1"
b110000101 %
#3900
0"
b110000110 %
#3910
1"
b110000111 %
#3920
0"
b110001000 %
#3930
1"
b110001001 %
#3940
0"
b110001010 %
#3950
1"
b110001011 %
#3960
0"
b110001100 %
#3970
1"
b110001101 %
#3980
0"
b110001110 %
#3990
1"
b110001111 %
#4000
0"
b110010000 %
#4010
1"
b110010001 %
#4020
0"
b110010010 %
#4030
1"
b110010011 %
#4040
0"
b110010100 %
#4050
1"
b110010101 %
#4060
0"
b110010110 %
#4070
1"
b110010111 %
#4080
0"
b110011000 %
#4090
1"
b110011001 %
#4100
0"
b110011010 %
#4110
1"
b110011011 %
#4120
0"
b110011100 %
#4130
1"
b110011101 %
#4140
0"
b110011110 %
#4150
1"
b110011111 %
#4160
0"
b110100000 %
#4170
1"
b110100001 %
#4180
0"
b110100010 %
#4190
1"
b110100011 %
#4200
0"
b110100100 %
#4210
1"
b110100101 %
#4220
0"
b110100110 %
#4230
1"
b110100111 %
#4240
0"
b110101000 %
#4250
1"
b110101001 %
#4260
0"
b110101010 %
#4270
1"
b110101011 %
#4280
0"
b110101100 %
#4290
1"
b110101101 %
#4300
0"
b110101110 %
#4310
1"
b110101111 %
#4320
0"
b110110000 %
#4330
1"
b110110001 %
#4340
0"
b110110010 %
#4350
1"
b110110011 %
#4360
0"
b110110100 %
#4370
1"
b110110101 %
#4380
0"
b110110110 %
#4390
1"
b110110111 %
#4400
0"
b110111000 %
#4410
1"
b110111001 %
#4420
0"
b110111010 %
#4430
1"
b110111011 %
#4440
0"
b110111100 %
#4450
1"
b110111101 %
#4460
0"
b110111110 %
#4470
1"
b110111111 %
#4480
0"
b111000000 %
#4490
1"
b111000001 %
#4500
0"
b111000010 %
#4510
1"
b111000011 %
#4520
0"
b111000100 %
#4530
1"
b111000101 %
#4540
0"
b111000110 %
#4550
1"
b111000111 %
#4560
0"
b111001000 %
#4570
1"
b111001001 %
#4580
0"
b111001010 %
#4590
1"
b111001011 %
#4600
0"
b111001100 %
#4610
1"
b111001101 %
#4620
0"
b111001110 %
#4630
1"
b111001111 %
#4640
0"
b111010000 %
#4650
1"
b111010001 %
#4660
0"
b111010010 %
#4670
1"
b111010011 %
#4680
0"
b111010100 %
#4690
1"
b111010101 %
#4700
0"
b111010110 %
#4710
1"
b111010111 %
#4720
0"
b111011000 %
#4730
1"
b111011001 %
#4740
0"
b111011010 %
#4750
1"
b111011011 %
#4760
0"
b111011100 %
#4770
1"
b111011101 %
#4780
0"
b111011110 %
#4790
1"
b111011111 %
#4800
0"
b111100000 %
#4810
1"
b111100001 %
#4820
0"
b111100010 %
#4830
1"
b111100011 %
#4840
0"
b111100100 %
#4850
1"
b111100101 %
#4860
0"
b111100110 %
#4870
1"
b111100111 %
#4880
0"
b111101000 %
#4890
1"
b111101001 %
#4900
0"
b111101010 %
#4910
1"
b111101011 %
#4920
0"
b111101100 %
#4930
1"
b111101101 %
#4940
0"
b111101110 %
#4950
1"
b111101111 %
#4960
0"
b111110000 %
#4970
1"
b111110001 %
#4980
0"
b111110010 %
#4990
1"
b111110011 %
#5000
0"
b111110100 %
#5010
1"
b111110101 %
#5020
0"
b111110110 %
#5030
1"
b111110111 %
#5040
0"
b111111000 %
#5050
1"
b111111001 %
#5060
0"
b111111010 %
#5070
1"
b111111011 %
#5080
0"
b111111100 %
#5090
1"
b111111101 %
#5100
0"
b111111110 %
#5110
1"
b111111111 %
#5120
0"
b1000000000 %
#5130
1"
b1000000001 %
#5140
0"
b1000000010 %
#5150
1"
b1000000011 %
#5160
0"
b1000000100 %
#5170
1"
b1000000101 %
#5180
0"
b1000000110 %
#5190
1"
b1000000111 %
#5200
0"
b1000001000 %
#5210
1"
b1000001001 %
#5220
0"
b1000001010 %
#5230
1"
b1000001011 %
#5240
0"
b1000001100 %
#5250
1"
b1000001101 %
#5260
0"
b1000001110 %
#5270
1"
b1000001111 %
#5280
0"
b1000010000 %
#5290
1"
b1000010001 %
#5300
0"
b1000010010 %
#5310
1"
b1000010011 %
#5320
0"
b1000010100 %
#5330
1"
b1000010101 %
#5340
0"
b1000010110 %
#5350
1"
b1000010111 %
#5360
0"
b1000011000 %
#5370
1"
b1000011001 %
#5380
0"
b1000011010 %
#5390
1"
b1000011011 %
#5400
0"
b1000011100 %
#5410
1"
b1000011101 %
#5420
0"
b1000011110 %
#5430
1"
b1000011111 %
#5440
0"
b1000100000 %
#5450
1"
b1000100001 %
#5460
0"
b1000100010 %
#5470
1"
b1000100011 %
#5480
0"
b1000100100 %
#5490
1"
b1000100101 %
#5500
0"
b1000100110 %
#5510
1"
b1000100111 %
#5520
0"
b1000101000 %
#5530
1"
b1000101001 %
#5540
0"
b1000101010 %
#5550
1"
b1000101011 %
#5560
0"
b1000101100 %
#5570
1"
b1000101101 %
#5580
0"
b1000101110 %
#5590
1"
b1000101111 %
#5600
0"
b1000110000 %
#5610
1"
b1000110001 %
#5620
0"
b1000110010 %
#5630
1"
b1000110011 %
#5640
0"
b1000110100 %
#5650
1"
b1000110101 %
#5660
0"
b1000110110 %
#5670
1"
b1000110111 %
#5680
0"
b1000111000 %
#5690
1"
b1000111001 %
#5700
0"
b1000111010 %
#5710
1"
b1000111011 %
#5720
0"
b1000111100 %
#5730
1"
b1000111101 %
#5740
0"
b1000111110 %
#5750
1"
b1000111111 %
#5760
0"
b1001000000 %
#5770
1"
b1001000001 %
#5780
0"
b1001000010 %
#5790
1"
b1001000011 %
#5800
0"
b1001000100 %
#5810
1"
b1001000101 %
#5820
0"
b1001000110 %
#5830
1"
b1001000111 %
#5840
0"
b1001001000 %
#5850
1"
b1001001001 %
#5860
0"
b1001001010 %
#5870
1"
b1001001011 %
#5880
0"
b1001001100 %
#5890
1"
b1001001101 %
#5900
0"
b1001001110 %
#5910
1"
b1001001111 %
#5920
0"
b1001010000 %
#5930
1"
b1001010001 %
#5940
0"
b1001010010 %
#5950
1"
b1001010011 %
#5960
0"
b1001010100 %
#5970
1"
b1001010101 %
#5980
0"
b1001010110 %
#5990
1"
b1001010111 %
#6000
0"
b1001011000 %
#6010
1"
b1001011001 %
#6020
0"
b1001011010 %
#6030
1"
b1001011011 %
#6040
0"
b1001011100 %
#6050
1"
b1001011101 %
#6060
0"
b1001011110 %
#6070
1"
b1001011111 %
#6080
0"
b1001100000 %
#6090
1"
b1001100001 %
#6100
0"
b1001100010 %
#6110
1"
b1001100011 %
#6120
0"
b1001100100 %
#6130
1"
b1001100101 %
#6140
0"
b1001100110 %
#6150
1"
b1001100111 %
#6160
0"
b1001101000 %
#6170
1"
b1001101001 %
#6180
0"
b1001101010 %
#6190
1"
b1001101011 %
#6200
0"
b1001101100 %
#6210
1"
b1001101101 %
#6220
0"
b1001101110 %
#6230
1"
b1001101111 %
#6240
0"
b1001110000 %
#6250
1"
b1001110001 %
#6260
0"
b1001110010 %
#6270
1"
b1001110011 %
#6280
0"
b1001110100 %
#6290
1"
b1001110101 %
#6300
0"
b1001110110 %
#6310
1"
b1001110111 %
#6320
0"
b1001111000 %
#6330
1"
b1001111001 %
#6340
0"
b1001111010 %
#6350
1"
b1001111011 %
#6360
0"
b1001111100 %
#6370
1"
b1001111101 %
#6380
0"
b1001111110 %
#6390
1"
b1001111111 %
#6400
0"
b1010000000 %
#6410
1"
b1010000001 %
#6420
0"
b1010000010 %
#6430
1"
b1010000011 %
#6440
0"
b1010000100 %
#6450
1"
b1010000101 %
#6460
0"
b1010000110 %
#6470
1"
b1010000111 %
#6480
0"
b1010001000 %
#6490
1"
b1010001001 %
#6500
0"
b1010001010 %
#6510
1"
b1010001011 %
#6520
0"
b1010001100 %
#6530
1"
b1010001101 %
#6540
0"
b1010001110 %
#6550
1"
b1010001111 %
#6560
0"
b1010010000 %
#6570
1"
b1010010001 %
#6580
0"
b1010010010 %
#6590
1"
b1010010011 %
#6600
0"
b1010010100 %
#6610
1"
b1010010101 %
#6620
0"
b1010010110 %
#6630
1"
b1010010111 %
#6640
0"
b1010011000 %
#6650
1"
b1010011001 %
#6660
0"
b1010011010 %
#6670
1"
b1010011011 %
#6680
0"
b1010011100 %
#6690
1"
b1010011101 %
#6700
0"
b1010011110 %
#6710
1"
b1010011111 %
#6720
0"
b1010100000 %
#6730
1"
b1010100001 %
#6740
0"
b1010100010 %
#6750
1"
b1010100011 %
#6760
0"
b1010100100 %
#6770
1"
b1010100101 %
#6780
0"
b1010100110 %
#6790
1"
b1010100111 %
#6800
0"
b1010101000 %
#6810
1"
b1010101001 %
#6820
0"
b1010101010 %
#6830
1"
b1010101011 %
#6840
0"
b1010101100 %
#6850
1"
b1010101101 %
#6860
0"
b1010101110 %
#6870
1"
b1010101111 %
#6880
0"
b1010110000 %
#6890
1"
b1010110001 %
#6900
0"
b1010110010 %
#6910
1"
b1010110011 %
#6920
0"
b1010110100 %
#6930
1"
b1010110101 %
#6940
0"
b1010110110 %
#6950
1"
b1010110111 %
#6960
0"
b1010111000 %
#6970
1"
b1010111001 %
#6980
0"
b1010111010 %
#6990
1"
b1010111011 %
#7000
0"
b1010111100 %
#7010
1"
b1010111101 %
#7020
0"
b1010111110 %
#7030
1"
b1010111111 %
#7040
0"
b1011000000 %
#7050
1"
b1011000001 %
#7060
0"
b1011000010 %
#7070
1"
b1011000011 %
#7080
0"
b1011000100 %
#7090
1"
b1011000101 %
#7100
0"
b1011000110 %
#7110
1"
b1011000111 %
#7120
0"
b1011001000 %
#7130
1"
b1011001001 %
#7140
0"
b1011001010 %
#7150
1"
b1011001011 %
#7160
0"
b1011001100 %
#7170
1"
b1011001101 %
#7180
0"
b1011001110 %
#7190
1"
b1011001111 %
#7200
0"
b1011010000 %
#7210
1"
b1011010001 %
#7220
0"
b1011010010 %
#7230
1"
b1011010011 %
#7240
0"
b1011010100 %
#7250
1"
b1011010101 %
#7260
0"
b1011010110 %
#7270
1"
b1011010111 %
#7280
0"
b1011011000 %
#7290
1"
b1011011001 %
#7300
0"
b1011011010 %
#7310
1"
b1011011011 %
#7320
0"
b1011011100 %
#7330
1"
b1011011101 %
#7340
0"
b1011011110 %
#7350
1"
b1011011111 %
#7360
0"
b1011100000 %
#7370
1"
b1011100001 %
#7380
0"
b1011100010 %
#7390
1"
b1011100011 %
#7400
0"
b1011100100 %
#7410
1"
b1011100101 %
#7420
0"
b1011100110 %
#7430
1"
b1011100111 %
#7440
0"
b1011101000 %
#7450
1"
b1011101001 %
#7460
0"
b1011101010 %
#7470
1"
b1011101011 %
#7480
0"
b1011101100 %
#7490
1"
b1011101101 %
#7500
0"
b1011101110 %
#7510
1"
b1011101111 %
#7520
0"
b1011110000 %
#7530
1"
b1011110001 %
#7540
0"
b1011110010 %
#7550
1"
b1011110011 %
#7560
0"
b1011110100 %
#7570
1"
b1011110101 %
#7580
0"
b1011110110 %
#7590
1"
b1011110111 %
#7600
0"
b1011111000 %
#7610
1"
b1011111001 %
#7620
0"
b1011111010 %
#7630
1"
b1011111011 %
#7640
0"
b1011111100 %
#7650
1"
b1011111101 %
#7660
0"
b1011111110 %
#7670
1"
b1011111111 %
#7680
0"
b1100000000 %
#7690
1"
b1100000001 %
#7700
0"
b1100000010 %
#7710
1"
b1100000011 %
#7720
0"
b1100000100 %
#7730
1"
b1100000101 %
#7740
0"
b1100000110 %
#7750
1"
b1100000111 %
#7760
0"
b1100001000 %
#7770
1"
b1100001001 %
#7780
0"
b1100001010 %
#7790
1"
b1100001011 %
#7800
0"
b1100001100 %
#7810
1"
b1100001101 %
#7820
0"
b1100001110 %
#7830
1"
b1100001111 %
#7840
0"
b1100010000 %
#7850
1"
b1100010001 %
#7860
0"
b1100010010 %
#7870
1"
b1100010011 %
#7880
0"
b1100010100 %
#7890
1"
b1100010101 %
#7900
0"
b1100010110 %
#7910
1"
b1100010111 %
#7920
0"
b1100011000 %
#7930
1"
b1100011001 %
#7940
0"
b1100011010 %
#7950
1"
b1100011011 %
#7960
0"
b1100011100 %
#7970
1"
b1100011101 %
#7980
0"
b1100011110 %
#7990
1"
b1100011111 %
#8000
0"
b1100100000 %
#8010
1"
b1100100001 %
#8020
0"
b1100100010 %
#8030
1"
b1100100011 %
#8040
0"
b1100100100 %
#8050
1"
b1100100101 %
#8060
0"
b1100100110 %
#8070
1"
b1100100111 %
#8080
0"
b1100101000 %
#8090
1"
b1100101001 %
#8100
0"
b1100101010 %
#8110
1"
b1100101011 %
#8120
0"
b1100101100 %
#8130
1"
b1100101101 %
#8140
0"
b1100101110 %
#8150
1"
b1100101111 %
#8160
0"
b1100110000 %
#8170
1"
b1100110001 %
#8180
0"
b1100110010 %
#8190
1"
b1100110011 %
#8200
0"
b1100110100 %
#8210
1"
b1100110101 %
#8220
0"
b1100110110 %
#8230
1"
b1100110111 %
#8240
0"
b1100111000 %
#8250
1"
b1100111001 %
#8260
0"
b1100111010 %
#8270
1"
b1100111011 %
#8280
0"
b1100111100 %
#8290
1"
b1100111101 %
#8300
0"
b1100111110 %
#8310
1"
b1100111111 %
#8320
0"
b1101000000 %
#8330
1"
b1101000001 %
#8340
0"
b1101000010 %
#8350
1"
b1101000011 %
#8360
0"
b1101000100 %
#8370
1"
b1101000101 %
#8380
0"
b1101000110 %
#8390
1"
b1101000111 %
#8400
0"
b1101001000 %
#8410
1"
b1101001001 %
#8420
0"
b1101001010 %
#8430
1"
b1101001011 %
#8440
0"
b1101001100 %
#8450
1"
b1101001101 %
#8460
0"
b1101001110 %
#8470
1"
b1101001111 %
#8480
0"
b1101010000 %
#8490
1"
b1101010001 %
#8500
0"
b1101010010 %
#8510
1"
b1101010011 %
#8520
0"
b1101010100 %
#8530
1"
b1101010101 %
#8540
0"
b1101010110 %
#8550
1"
b1101010111 %
#8560
0"
b1101011000 %
#8570
1"
b1101011001 %
#8580
0"
b1101011010 %
#8590
1"
b1101011011 %
#8600
0"
b1101011100 %
#8610
1"
b1101011101 %
#8620
0"
b1101011110 %
#8630
1"
b1101011111 %
#8640
0"
b1101100000 %
#8650
1"
b1101100001 %
#8660
0"
b1101100010 %
#8670
1"
b1101100011 %
#8680
0"
b1101100100 %
#8690
1"
b1101100101 %
#8700
0"
b1101100110 %
#8710
1"
b1101100111 %
#8720
0"
b1101101000 %
#8730
1"
b1101101001 %
#8740
0"
b1101101010 %
#8750
1"
b1101101011 %
#8760
0"
b1101101100 %
#8770
1"
b1101101101 %
#8780
0"
b1101101110 %
#8790
1"
b1101101111 %
#8800
0"
b1101110000 %
#8810
1"
b1101110001 %
#8820
0"
b1101110010 %
#8830
1"
b1101110011 %
#8840
0"
b1101110100 %
#8850
1"
b1101110101 %
#8860
0"
b1101110110 %
#8870
1"
b1101110111 %
#8880
0"
b1101111000 %
#8890
1"
b1101111001 %
#8900
0"
b1101111010 %
#8910
1"
b1101111011 %
#8920
0"
b1101111100 %
#8930
1"
b1101111101 %
#8940
0"
b1101111110 %
#8950
1"
b1101111111 %
#8960
0"
b1110000000 %
#8970
1"
b1110000001 %
#8980
0"
b1110000010 %
#8990
1"
b1110000011 %
#9000
0"
b1110000100 %
#9010
1"
b1110000101 %
#9020
0"
b1110000110 %
#9030
1"
b1110000111 %
#9040
0"
b1110001000 %
#9050
1"
b1110001001 %
#9060
0"
b1110001010 %
#9070
1"
b1110001011 %
#9080
0"
b1110001100 %
#9090
1"
b1110001101 %
#9100
0"
b1110001110 %
#9110
1"
b1110001111 %
#9120
0"
b1110010000 %
#9130
1"
b1110010001 %
#9140
0"
b1110010010 %
#9150
1"
b1110010011 %
#9160
0"
b1110010100 %
#9170
1"
b1110010101 %
#9180
0"
b1110010110 %
#9190
1"
b1110010111 %
#9200
0"
b1110011000 %
#9210
1"
b1110011001 %
#9220
0"
b1110011010 %
#9230
1"
b1110011011 %
#9240
0"
b1110011100 %
#9250
1"
b1110011101 %
#9260
0"
b1110011110 %
#9270
1"
b1110011111 %
#9280
0"
b1110100000 %
#9290
1"
b1110100001 %
#9300
0"
b1110100010 %
#9310
1"
b1110100011 %
#9320
0"
b1110100100 %
#9330
1"
b1110100101 %
#9340
0"
b1110100110 %
#9350
1"
b1110100111 %
#9360
0"
b1110101000 %
#9370
1"
b1110101001 %
#9380
0"
b1110101010 %
#9390
1"
b1110101011 %
#9400
0"
b1110101100 %
#9410
1"
b1110101101 %
#9420
0"
b1110101110 %
#9430
1"
b1110101111 %
#9440
0"
b1110110000 %
#9450
1"
b1110110001 %
#9460
0"
b1110110010 %
#9470
1"
b1110110011 %
#9480
0"
b1110110100 %
#9490
1"
b1110110101 %
#9500
0"
b1110110110 %
#9510
1"
b1110110111 %
#9520
0"
b1110111000 %
#9530
1"
b1110111001 %
#9540
0"
b1110111010 %
