sequential_circuits/finite_state_machines/sequence_detector1.v
//Sequence detector for 1010

module sequence_detector1(o, i, clk, rst);
    input i, clk, rst;
    output reg o;

    reg [1:0] state;

    always @(posedge clk) begin
        if (rst) state <= 2'b00;
        else begin
            case (state)
                2'b00: begin
                    if (i == 1) state <= 2'b01;
                    o <= 0;
                end
                2'b01: begin
                    if (i == 0) state <= 2'b10;
                    o <= 0;
                end
                2'b10: begin
                    if (i == 1) state <= 2'b11;
                    else state <= 2'b00;
                    o <= 0;
                end
                2'b11: begin
                    if (i == 0) begin
                        state <= 2'b10;
                        o <= 1;
                    end
                    else begin
                        state <= 2'b01;
                        o <= 0;
                    end
                end
            endcase
        end
    end
endmodule

sequential_circuits/finite_state_machines/sequence_detector1_tb.v
`timescale 1ps/1ps
`include "sequence_detector1.v"

module sequence_detector1_tb;
    reg i, clk, rst;
    wire o;

    integer bit_stream = 20'b0101_1010_1010_1110_1010;
    integer j = 0;

    sequence_detector1 sd11(o, i, clk, rst);

    always #10 clk = ~clk;

    initial begin
        rst = 1; clk = 0; j = 0;
        #30 rst = 0;
        for (j = 19; j >= 0; j = j-1) begin
            #20 i = bit_stream[j];
        end
    end

    initial begin
        $dumpfile("seq1.vcd");
        $dumpvars;
        #1000 $finish;
    end
endmodule

sequential_circuits/finite_state_machines/seq1.vcd
$date
	Mon Jan  8 00:03:53 2024
$end
$version
	Icarus Verilog
$end
$timescale
	1ps
$end
$scope module sequence_detector1_tb $end
$var wire 1 ! o $end
$var reg 1 " clk $end
$var reg 1 # i $end
$var reg 1 $ rst $end
$var integer 32 % bit_stream [31:0] $end
$var integer 32 & j [31:0] $end
$scope module sd11 $end
$var wire 1 " clk $end
$var wire 1 # i $end
$var wire 1 $ rst $end
$var reg 1 ! o $end
$var reg 2 ' state [1:0] $end
$upscope $end
$upscope $end
$enddefinitions $end
$comment Show the parameter values. $end
$dumpall
$end
#0
$dumpvars
bx '
b0 &
b1011010101011101010 %
1$
x#
0"
x!
$end
#10
b0 '
1"
#20
0"
#30
0!
1"
b10011 &
0$
#40
0"
#50
1"
b10010 &
0#
#60
0"
#70
b1 '
1"
b10001 &
1#
#80
0"
#90
b10 '
1"
b10000 &
0#
#100
0"
#110
b11 '
1"
b1111 &
1#
#120
0"
#130
b1 '
1"
b1110 &
#140
0"
#150
b10 '
1"
b1101 &
0#
#160
0"
#170
b11 '
1"
b1100 &
1#
#180
0"
#190
1!
b10 '
1"
b1011 &
0#
#200
0"
#210
0!
b11 '
1"
b1010 &
1#
#220
0"
#230
1!
b10 '
1"
b1001 &
0#
#240
0"
#250
0!
b11 '
1"
b1000 &
1#
#260
0"
#270
1!
b10 '
1"
b111 &
0#
#280
0"
#290
0!
b11 '
1"
b110 &
1#
#300
0"
#310
b1 '
1"
b101 &
#320
0"
#330
1"
b100 &
#340
0"
#350
b10 '
1"
b11 &
0#
#360
0"
#370
b11 '
1"
b10 &
1#
#380
0"
#390
1!
b10 '
1"
b1 &
0#
#400
0"
#410
0!
b11 '
1"
b0 &
1#
#420
0"
#430
1!
b10 '
1"
b11111111111111111111111111111111 &
0#
#440
0"
#450
0!
b0 '
1"
