sequential_circuits/finite_state_machines/Multiplier/multiplier_fsmd.v
module multiplier(a_in, b_in, result, clk, reset, start, ready);
    input [3:0] a_in, b_in;
    input clk, reset, start;
    output reg ready;
    output reg [8:0] result;

    reg [3:0] a_reg;
    reg [1:0] state;
    reg [7:0] counter;

    always @(posedge clk) begin
        if (reset) begin
            state <= 2'b00; 
            counter <= 8'b0;
            a_reg <= 4'd0;
            ready <= 0;
            result <= 9'd0;
        end
        else begin
            case (state)
                2'b00: begin //Idle state
                    if (start == 1) state <= 2'b01;
                    ready <= 1;
                end

                2'b01: begin //Load state
                    counter <= 0;
                    result <= 9'd0 + b_in;
                    a_reg <= a_in;
                    state <= 2'b10;
                    ready <= 0;
                end
                
                2'b10: begin //op state
                    counter <= counter + 1;
                    if (result[0] == 1) begin
                        result <= {1'b0, (result[8:4] + {1'b0, a_in}), result[3:1]};
                    end
                    else
                        result <= {1'b0, result[8:1]};
                    if (counter == 3)
                        state <= 2'b00;
                    ready <= 0;
                end
            endcase
        end
    end
endmodule

sequential_circuits/finite_state_machines/Multiplier/multiplier_fsmd_tb.v
`timescale 1ps/1ps
`include "multiplier_fsmd.v"

module multiplier_fsmd_tb;
    reg [3:0] a_in, b_in;
    reg clk, reset, start;
    wire ready;
    wire [8:0]result;

    multiplier ml1(a_in, b_in, result, clk, reset, start, ready);

    always #10 clk = ~clk;

    initial begin
        reset = 1; clk = 0; a_in = 4'b0000; b_in = 4'b0000; start = 0;
        #30 reset = 0; start = 1; a_in = 4'd11; b_in = 4'd9;
        #20 start = 0;
    end

    initial begin
        $dumpfile("multiplier.vcd");
        $dumpvars;
        #1000 $finish;
    end
endmodule

sequential_circuits/finite_state_machines/Multiplier/multiplier.vcd
$date
	Tue Apr 16 17:34:04 2024
$end
$version
	Icarus Verilog
$end
$timescale
	1ps
$end
$scope module multiplier_fsmd_tb $end
$var wire 9 ! result [8:0] $end
$var wire 1 " ready $end
$var reg 4 # a_in [3:0] $end
$var reg 4 $ b_in [3:0] $end
$var reg 1 % clk $end
$var reg 1 & reset $end
$var reg 1 ' start $end
$scope module ml1 $end
$var wire 4 ( a_in [3:0] $end
$var wire 4 ) b_in [3:0] $end
$var wire 1 % clk $end
$var wire 1 & reset $end
$var wire 1 ' start $end
$var reg 4 * a_reg [3:0] $end
$var reg 8 + counter [7:0] $end
$var reg 1 " ready $end
$var reg 9 , result [8:0] $end
$var reg 2 - state [1:0] $end
$upscope $end
$upscope $end
$enddefinitions $end
$comment Show the parameter values. $end
$dumpall
$end
#0
$dumpvars
bx -
bx ,
bx +
bx *
b0 )
b0 (
0'
1&
0%
b0 $
b0 #
x"
bx !
$end
#10
b0 !
b0 ,
0"
b0 *
b0 +
b0 -
1%
#20
0%
#30
1"
b1 -
1%
b1001 $
b1001 )
b1011 #
b1011 (
1'
0&
#40
0%
#50
0"
b10 -
b1011 *
b1001 !
b1001 ,
1%
0'
#60
0%
#70
b1011100 !
b1011100 ,
b1 +
1%
#80
0%
#90
b101110 !
b101110 ,
b10 +
1%
#100
0%
#110
b10111 !
b10111 ,
b11 +
1%
#120
0%
#130
b0 -
b1100011 !
b1100011 ,
b100 +
1%
#140
0%
#150
1"
1%
