sequential_circuits/fifo/dual_clock_fifo.v
module dual_clock_fifo(clk_wr, wr_en, wr_data, full, clk_rd, rd_en, rd_data, empty, rst);
    parameter fifo_depth = 16;
    parameter fifo_width = 8; 

    input wr_en, rd_en, clk_wr, clk_rd, rst;
    input [fifo_width-1:0] wr_data;
    output full, empty;
    output [fifo_width-1:0] rd_data;

    reg [fifo_width-1:0] mem_buffer[0:fifo_depth-1];
    reg [$clog2(fifo_depth):0] wr_ptr, rd_ptr;
    reg [fifo_width-1:0] rd_data2;

    always @(posedge clk_wr) begin
        if (rst) wr_ptr <= 0;
        else begin
            if (wr_en & !full) begin
                mem_buffer[wr_ptr] <= wr_data;
                wr_ptr <= wr_ptr + 1;
            end
        end
    end

    always @(posedge clk_rd) begin
        if (rst) begin
            rd_data2 <= 0;
            rd_ptr <= 0;
        end
        else begin
            if (rd_en & !empty) begin
                rd_data2 <= mem_buffer[rd_ptr];
                rd_ptr <= rd_ptr + 1;
            end
            else rd_data2 <= rd_data2;
        end
    end

    assign full = (wr_ptr == fifo_depth) ? 1:0;
    assign rd_data = rd_data2;
    assign empty = (rd_ptr < wr_ptr) ? 0:1;
endmodule

sequential_circuits/fifo/dual_clock_fifo_tb.v
`timescale 1ps/1ps
`include "dual_clock_fifo.v"

module dual_clock_fifo_tb;
    parameter fifo_depth = 64;
    parameter fifo_width = 8; 

    reg wr_en, rd_en, clk_wr, clk_rd, rst;
    reg [fifo_width-1:0] wr_data;
    wire full, empty;
    wire [fifo_width-1:0] rd_data;
    integer i;

    dual_clock_fifo dcf1(clk_wr, wr_en, wr_data, full, clk_rd, rd_en, rd_data, empty, rst);

    always #20 clk_wr = ~clk_wr;
    always #10 clk_rd = ~clk_rd;
    initial begin
        $dumpfile ("dual_clock_fifo.vcd");
        $dumpvars;
        wr_en = 0; rd_en = 0; clk_wr = 0; clk_rd = 0; wr_data = 0; rst = 1;
        $monitor("time = %d \t rst = %b \t wr_en = %b \t wr_data = %h full = %b \t rd_en = %b \t rd_data = %h", $time, rst, wr_en, wr_data, full, rd_en, rd_data);
        #100 rst = 0; wr_en = 1; wr_data = $random;
        for (i = 0; i < 20; i = i+1) begin
            #40 wr_data = $random;
        end
    end
    initial begin
        #1000 rd_en = 1;
        #10000 
        $display("----------------------- The simulation has ended -------------------------");
        $finish;
    end
endmodule

sequential_circuits/fifo/dual_clock_fifo.vcd
$date
	Sat Jan  6 23:18:50 2024
$end
$version
	Icarus Verilog
$end
$timescale
	1ps
$end
$scope module dual_clock_fifo_tb $end
$var wire 8 ! rd_data [7:0] $end
$var wire 1 " full $end
$var wire 1 # empty $end
$var parameter 32 $ fifo_depth $end
$var parameter 32 % fifo_width $end
$var reg 1 & clk_rd $end
$var reg 1 ' clk_wr $end
$var reg 1 ( rd_en $end
$var reg 1 ) rst $end
$var reg 8 * wr_data [7:0] $end
$var reg 1 + wr_en $end
$var integer 32 , i [31:0] $end
$scope module dcf1 $end
$var wire 1 & clk_rd $end
$var wire 1 ' clk_wr $end
$var wire 8 - rd_data [7:0] $end
$var wire 1 ( rd_en $end
$var wire 1 ) rst $end
$var wire 8 . wr_data [7:0] $end
$var wire 1 + wr_en $end
$var wire 1 " full $end
$var wire 1 # empty $end
$var parameter 32 / fifo_depth $end
$var parameter 32 0 fifo_width $end
$var reg 8 1 rd_data2 [7:0] $end
$var reg 5 2 rd_ptr [4:0] $end
$var reg 5 3 wr_ptr [4:0] $end
$upscope $end
$upscope $end
$enddefinitions $end
$comment Show the parameter values. $end
$dumpall
b1000 0
b10000 /
b1000 %
b1000000 $
$end
#0
$dumpvars
bx 3
bx 2
bx 1
b0 .
bx -
bx ,
0+
b0 *
1)
0(
0'
0&
x#
x"
bx !
$end
#10
b0 2
b0 !
b0 -
b0 1
1&
#20
0"
1#
b0 3
0&
1'
#30
1&
#40
0&
0'
#50
1&
#60
0&
1'
#70
1&
#80
0&
0'
#90
1&
#100
0#
b1 3
0&
1'
b0 ,
b100100 *
b100100 .
1+
0)
#110
1&
#120
0&
0'
#130
1&
#140
b10 3
0&
1'
b1 ,
b10000001 *
b10000001 .
#150
1&
#160
0&
0'
#170
1&
#180
b11 3
0&
1'
b10 ,
b1001 *
b1001 .
#190
1&
#200
0&
0'
#210
1&
#220
b100 3
0&
1'
b11 ,
b1100011 *
b1100011 .
#230
1&
#240
0&
0'
#250
1&
#260
b101 3
0&
1'
b100 ,
b1101 *
b1101 .
#270
1&
#280
0&
0'
#290
1&
#300
b110 3
0&
1'
b101 ,
b10001101 *
b10001101 .
#310
1&
#320
0&
0'
#330
1&
#340
b111 3
0&
1'
b110 ,
b1100101 *
b1100101 .
#350
1&
#360
0&
0'
#370
1&
#380
b1000 3
0&
1'
b111 ,
b10010 *
b10010 .
#390
1&
#400
0&
0'
#410
1&
#420
b1001 3
0&
1'
b1000 ,
b1 *
b1 .
#430
1&
#440
0&
0'
#450
1&
#460
b1010 3
0&
1'
b1001 ,
b1101 *
b1101 .
#470
1&
#480
0&
0'
#490
1&
#500
b1011 3
0&
1'
b1010 ,
b1110110 *
b1110110 .
#510
1&
#520
0&
0'
#530
1&
#540
b1100 3
0&
1'
b1011 ,
b111101 *
b111101 .
#550
1&
#560
0&
0'
#570
1&
#580
b1101 3
0&
1'
b1100 ,
b11101101 *
b11101101 .
#590
1&
#600
0&
0'
#610
1&
#620
b1110 3
0&
1'
b1101 ,
b10001100 *
b10001100 .
#630
1&
#640
0&
0'
#650
1&
#660
b1111 3
0&
1'
b1110 ,
b11111001 *
b11111001 .
#670
1&
#680
0&
0'
#690
1&
#700
1"
b10000 3
0&
1'
b1111 ,
b11000110 *
b11000110 .
#710
1&
#720
0&
0'
#730
1&
#740
0&
1'
b10000 ,
b11000101 *
b11000101 .
#750
1&
#760
0&
0'
#770
1&
#780
0&
1'
b10001 ,
b10101010 *
b10101010 .
#790
1&
#800
0&
0'
#810
1&
#820
0&
1'
b10010 ,
b11100101 *
b11100101 .
#830
1&
#840
0&
0'
#850
1&
#860
0&
1'
b10011 ,
b1110111 *
b1110111 .
#870
1&
#880
0&
0'
#890
1&
#900
0&
1'
b10100 ,
b10010 *
b10010 .
#910
1&
#920
0&
0'
#930
1&
#940
0&
1'
#950
1&
#960
0&
0'
#970
1&
#980
0&
1'
#990
1&
#1000
0&
0'
1(
#1010
b1 2
b100100 !
b100100 -
b100100 1
1&
#1020
0&
1'
#1030
b10 2
b10000001 !
b10000001 -
b10000001 1
1&
#1040
0&
0'
#1050
b11 2
b1001 !
b1001 -
b1001 1
1&
#1060
0&
1'
#1070
b100 2
b1100011 !
b1100011 -
b1100011 1
1&
#1080
0&
0'
#1090
b101 2
b1101 !
b1101 -
b1101 1
1&
#1100
0&
1'
#1110
b110 2
b10001101 !
b10001101 -
b10001101 1
1&
#1120
0&
0'
#1130
b111 2
b1100101 !
b1100101 -
b1100101 1
1&
#1140
0&
1'
#1150
b1000 2
b10010 !
b10010 -
b10010 1
1&
#1160
0&
0'
#1170
b1001 2
b1 !
b1 -
b1 1
1&
#1180
0&
1'
#1190
b1010 2
b1101 !
b1101 -
b1101 1
1&
#1200
0&
0'
#1210
b1011 2
b1110110 !
b1110110 -
b1110110 1
1&
#1220
0&
1'
#1230
b1100 2
b111101 !
b111101 -
b111101 1
1&
#1240
0&
0'
#1250
b1101 2
b11101101 !
b11101101 -
b11101101 1
1&
#1260
0&
1'
#1270
b1110 2
b10001100 !
b10001100 -
b10001100 1
1&
#1280
0&
0'
#1290
b1111 2
b11111001 !
b11111001 -
b11111001 1
1&
#1300
0&
1'
#1310
1#
b10000 2
b11000110 !
b11000110 -
b11000110 1
1&
