sequential_circuits/fifo/single_clock_fifo.v
module FIFO(clk, wr_en, wr_data, full, rd_en, rd_data, empty, rst);
    input clk, wr_en, rd_en, rst;
    input [7:0] wr_data;
    output full, empty;
    output [7:0] rd_data;

    reg [7:0] rd_data2;
    reg [7:0] mem_buffer[31:0];
    reg [5:0] wr_ptr, rd_ptr;

    always @(posedge clk) begin
        if (rst) begin
            wr_ptr <= 0;
            rd_ptr <= 0;
        end
    end

    always @(posedge clk) begin
        if (wr_en & !full & !rst) begin
            mem_buffer[wr_ptr] <= wr_data;
            wr_ptr <= wr_ptr + 1;
        end
    end

    always @(posedge clk) begin
        if (rst) rd_data2 <= 0;
        else begin
            if (rd_en & !empty) begin
                rd_data2 <= mem_buffer[rd_ptr];
                rd_ptr <= rd_ptr + 1;
            end
            else rd_data2 <= rd_data2;
        end
    end

    assign full = (wr_ptr == 6'd32) ? 1:0;
    assign empty = ((rd_ptr <= wr_ptr) & (rd_ptr <= 6'd32)) ? 0:1;
    assign rd_data = rd_data2;

endmodule

sequential_circuits/fifo/single_clock_fifo_tb.v
`timescale 1ps/1ps
`include "single_clock_fifo.v"

`define DELAY 10

module single_clock_fifo_tb;
    reg clk, wr_en, rd_en, rst;
    reg [7:0] wr_data;
    wire full, empty;
    wire [7:0] rd_data;

    parameter endtime = 10000;

    integer i;

    FIFO F1(clk, wr_en, wr_data, full, rd_en, rd_data, empty, rst);

    initial begin
        clk = 1'b0; rst = 1'b1; wr_en = 1'b0; rd_en = 1'b0;
        wr_data = 8'd0;
    end

    initial begin
        $dumpfile("single_clock_fifo.vcd");
        $dumpvars;
        main;
    end

    task main;
        fork 
            clock_generator;
            operation_process;
            simulation_result;
            endsimulation;
        join
    endtask

    task clock_generator;
        begin
            forever #`DELAY clk = !clk;
        end
    endtask

    task operation_process;
        begin
            #(`DELAY*10+`DELAY) rst = 0; wr_en = 1'b1; wr_data = $random;
            for (i = 0; i < 50; i = i+1) begin
                #(`DELAY*2) wr_data = $random;
            end
            rd_en = 1;
            for (i = 0; i < 100; i = i+1) begin
                #(`DELAY*2) wr_data = $random;
            end
        end
    endtask

    task simulation_result;
        begin
            $monitor("time = %d \t rst = %b \t rd_en = %b \t wr_en = %b \t wr_data = %h \t rd_data = %h \t full = %b \t empty = %b", $time, rst, rd_en, wr_en, wr_data, rd_data, full, empty);
        end
    endtask

    task endsimulation;
        begin
            #endtime 
            $display("-----------------The Simulation Ended---------------");
            $finish;
        end
    endtask

endmodule

sequential_circuits/fifo/single_clock_fifo.vcd
$date
	Thu Jan  4 23:59:18 2024
$end
$version
	Icarus Verilog
$end
$timescale
	1ps
$end
$scope module single_clock_fifo_tb $end
$var wire 8 ! rd_data [7:0] $end
$var wire 1 " full $end
$var wire 1 # empty $end
$var parameter 32 $ endtime $end
$var reg 1 % clk $end
$var reg 1 & rd_en $end
$var reg 1 ' rst $end
$var reg 8 ( wr_data [7:0] $end
$var reg 1 ) wr_en $end
$var integer 32 * i [31:0] $end
$scope module F1 $end
$var wire 1 % clk $end
$var wire 8 + rd_data [7:0] $end
$var wire 1 & rd_en $end
$var wire 1 ' rst $end
$var wire 8 , wr_data [7:0] $end
$var wire 1 ) wr_en $end
$var wire 1 " full $end
$var wire 1 # empty $end
$var reg 8 - rd_data2 [7:0] $end
$var reg 6 . rd_ptr [5:0] $end
$var reg 6 / wr_ptr [5:0] $end
$upscope $end
$scope task clock_generator $end
$upscope $end
$scope task endsimulation $end
$upscope $end
$scope task main $end
$upscope $end
$scope task operation_process $end
$upscope $end
$scope task simulation_result $end
$upscope $end
$upscope $end
$enddefinitions $end
$comment Show the parameter values. $end
$dumpall
b10011100010000 $
$end
#0
$dumpvars
bx /
bx .
bx -
b0 ,
bx +
bx *
0)
b0 (
1'
0&
0%
x#
x"
bx !
$end
#10
0#
0"
b0 .
b0 /
b0 !
b0 +
b0 -
1%
#20
0%
#30
1%
#40
0%
#50
1%
#60
0%
#70
1%
#80
0%
#90
1%
#100
0%
#110
b1 /
1%
b0 *
b100100 (
b100100 ,
1)
0'
#120
0%
#130
b10 /
1%
b1 *
b10000001 (
b10000001 ,
#140
0%
#150
b11 /
1%
b10 *
b1001 (
b1001 ,
#160
0%
#170
b100 /
1%
b11 *
b1100011 (
b1100011 ,
#180
0%
#190
b101 /
1%
b100 *
b1101 (
b1101 ,
#200
0%
#210
b110 /
1%
b101 *
b10001101 (
b10001101 ,
#220
0%
#230
b111 /
1%
b110 *
b1100101 (
b1100101 ,
#240
0%
#250
b1000 /
1%
b111 *
b10010 (
b10010 ,
#260
0%
#270
b1001 /
1%
b1000 *
b1 (
b1 ,
#280
0%
#290
b1010 /
1%
b1001 *
b1101 (
b1101 ,
#300
0%
#310
b1011 /
1%
b1010 *
b1110110 (
b1110110 ,
#320
0%
#330
b1100 /
1%
b1011 *
b111101 (
b111101 ,
#340
0%
#350
b1101 /
1%
b1100 *
b11101101 (
b11101101 ,
#360
0%
#370
b1110 /
1%
b1101 *
b10001100 (
b10001100 ,
#380
0%
#390
b1111 /
1%
b1110 *
b11111001 (
b11111001 ,
#400
0%
#410
b10000 /
1%
b1111 *
b11000110 (
b11000110 ,
#420
0%
#430
b10001 /
1%
b10000 *
b11000101 (
b11000101 ,
#440
0%
#450
b10010 /
1%
b10001 *
b10101010 (
b10101010 ,
#460
0%
#470
b10011 /
1%
b10010 *
b11100101 (
b11100101 ,
#480
0%
#490
b10100 /
1%
b10011 *
b1110111 (
b1110111 ,
#500
0%
#510
b10101 /
1%
b10100 *
b10010 (
b10010 ,
#520
0%
#530
b10110 /
1%
b10101 *
b10001111 (
b10001111 ,
#540
0%
#550
b10111 /
1%
b10110 *
b11110010 (
b11110010 ,
#560
0%
#570
b11000 /
1%
b10111 *
b11001110 (
b11001110 ,
#580
0%
#590
b11001 /
1%
b11000 *
b11101000 (
b11101000 ,
#600
0%
#610
b11010 /
1%
b11001 *
b11000101 (
b11000101 ,
#620
0%
#630
b11011 /
1%
b11010 *
b1011100 (
b1011100 ,
#640
0%
#650
b11100 /
1%
b11011 *
b10111101 (
b10111101 ,
#660
0%
#670
b11101 /
1%
b11100 *
b101101 (
b101101 ,
#680
0%
#690
b11110 /
1%
b11101 *
b1100101 (
b1100101 ,
#700
0%
#710
b11111 /
1%
b11110 *
b1100011 (
b1100011 ,
#720
0%
#730
1"
b100000 /
1%
b11111 *
b1010 (
b1010 ,
#740
0%
#750
1%
b100000 *
b10000000 (
b10000000 ,
#760
0%
#770
1%
b100001 *
b100000 (
b100000 ,
#780
0%
#790
1%
b100010 *
b10101010 (
b10101010 ,
#800
0%
#810
1%
b100011 *
b10011101 (
b10011101 ,
#820
0%
#830
1%
b100100 *
b10010110 (
b10010110 ,
#840
0%
#850
1%
b100101 *
b10011 (
b10011 ,
#860
0%
#870
1%
b100110 *
b1101 (
b1101 ,
#880
0%
#890
1%
b100111 *
b1010011 (
b1010011 ,
#900
0%
#910
1%
b101000 *
b1101011 (
b1101011 ,
#920
0%
#930
1%
b101001 *
b11010101 (
b11010101 ,
#940
0%
#950
1%
b101010 *
b10 (
b10 ,
#960
0%
#970
1%
b101011 *
b10101110 (
b10101110 ,
#980
0%
#990
1%
b101100 *
b11101 (
b11101 ,
#1000
0%
#1010
1%
b101101 *
b11001111 (
b11001111 ,
#1020
0%
#1030
1%
b101110 *
b100011 (
b100011 ,
#1040
0%
#1050
1%
b101111 *
b1010 (
b1010 ,
#1060
0%
#1070
1%
b110000 *
b11001010 (
b11001010 ,
#1080
0%
#1090
1%
b110001 *
b111100 (
b111100 ,
#1100
0%
#1110
b1 .
b100100 !
b100100 +
b100100 -
1%
1&
b0 *
b11110010 (
b11110010 ,
#1120
0%
#1130
b10 .
b10000001 !
b10000001 +
b10000001 -
1%
b1 *
b10001010 (
b10001010 ,
#1140
0%
#1150
b11 .
b1001 !
b1001 +
b1001 -
1%
b10 *
b1000001 (
b1000001 ,
#1160
0%
#1170
b100 .
b1100011 !
b1100011 +
b1100011 -
1%
b11 *
b11011000 (
b11011000 ,
#1180
0%
#1190
b101 .
b1101 !
b1101 +
b1101 -
1%
b100 *
b1111000 (
b1111000 ,
#1200
0%
#1210
b110 .
b10001101 !
b10001101 +
b10001101 -
1%
b101 *
b10001001 (
b10001001 ,
#1220
0%
#1230
b111 .
b1100101 !
b1100101 +
b1100101 -
1%
b110 *
b11101011 (
b11101011 ,
#1240
0%
#1250
b1000 .
b10010 !
b10010 +
b10010 -
1%
b111 *
b10110110 (
b10110110 ,
#1260
0%
#1270
b1001 .
b1 !
b1 +
b1 -
1%
b1000 *
b11000110 (
b11000110 ,
#1280
0%
#1290
b1010 .
b1101 !
b1101 +
b1101 -
1%
b1001 *
b10101110 (
b10101110 ,
#1300
0%
#1310
b1011 .
b1110110 !
b1110110 +
b1110110 -
1%
b1010 *
b10111100 (
b10111100 ,
#1320
0%
#1330
b1100 .
b111101 !
b111101 +
b111101 -
1%
b1011 *
b101010 (
b101010 ,
#1340
0%
#1350
b1101 .
b11101101 !
b11101101 +
b11101101 -
1%
b1100 *
b1011 (
b1011 ,
#1360
0%
#1370
b1110 .
b10001100 !
b10001100 +
b10001100 -
1%
b1101 *
b1110001 (
b1110001 ,
#1380
0%
#1390
b1111 .
b11111001 !
b11111001 +
b11111001 -
1%
b1110 *
b10000101 (
b10000101 ,
#1400
0%
#1410
b10000 .
b11000110 !
b11000110 +
b11000110 -
1%
b1111 *
b1001111 (
b1001111 ,
#1420
0%
#1430
b10001 .
b11000101 !
b11000101 +
b11000101 -
1%
b10000 *
b111011 (
b111011 ,
#1440
0%
#1450
b10010 .
b10101010 !
b10101010 +
b10101010 -
1%
b10001 *
b111010 (
b111010 ,
#1460
0%
#1470
b10011 .
b11100101 !
b11100101 +
b11100101 -
1%
b10010 *
b1111110 (
b1111110 ,
#1480
0%
#1490
b10100 .
b1110111 !
b1110111 +
b1110111 -
1%
b10011 *
b10101 (
b10101 ,
#1500
0%
#1510
b10101 .
b10010 !
b10010 +
b10010 -
1%
b10100 *
b11110001 (
b11110001 ,
#1520
0%
#1530
b10110 .
b10001111 !
b10001111 +
b10001111 -
1%
b10101 *
b11011001 (
b11011001 ,
#1540
0%
#1550
b10111 .
b11110010 !
b11110010 +
b11110010 -
1%
b10110 *
b1100010 (
b1100010 ,
#1560
0%
#1570
b11000 .
b11001110 !
b11001110 +
b11001110 -
1%
b10111 *
b1001100 (
b1001100 ,
#1580
0%
#1590
b11001 .
b11101000 !
b11101000 +
b11101000 -
1%
b11000 *
b10011111 (
b10011111 ,
#1600
0%
#1610
b11010 .
b11000101 !
b11000101 +
b11000101 -
1%
b11001 *
b10001111 (
b10001111 ,
#1620
0%
#1630
b11011 .
b1011100 !
b1011100 +
b1011100 -
1%
b11010 *
b11111000 (
b11111000 ,
#1640
0%
#1650
b11100 .
b10111101 !
b10111101 +
b10111101 -
1%
b11011 *
b10110111 (
b10110111 ,
#1660
0%
#1670
b11101 .
b101101 !
b101101 +
b101101 -
1%
b11100 *
b10011111 (
b10011111 ,
#1680
0%
#1690
b11110 .
b1100101 !
b1100101 +
b1100101 -
1%
b11101 *
b1011100 (
b1011100 ,
#1700
0%
#1710
b11111 .
b1100011 !
b1100011 +
b1100011 -
1%
b11110 *
b1011011 (
b1011011 ,
#1720
0%
#1730
b100000 .
b1010 !
b1010 +
b1010 -
1%
b11111 *
b10001001 (
b10001001 ,
#1740
0%
#1750
1#
b100001 .
bx !
bx +
bx -
1%
b100000 *
b1001001 (
b1001001 ,
#1760
0%
#1770
1%
b100001 *
b11010000 (
b11010000 ,
#1780
0%
#1790
1%
b100010 *
b11010111 (
b11010111 ,
#1800
0%
#1810
1%
b100011 *
b1010001 (
b1010001 ,
#1820
0%
#1830
1%
b100100 *
b10010110 (
b10010110 ,
#1840
0%
#1850
1%
b100101 *
b1100 (
b1100 ,
#1860
0%
#1870
1%
b100110 *
b11000010 (
b11000010 ,
#1880
0%
#1890
1%
b100111 *
b11001000 (
b11001000 ,
#1900
0%
#1910
1%
b101000 *
b1110111 (
b1110111 ,
#1920
0%
#1930
1%
b101001 *
b111101 (
b111101 ,
#1940
0%
#1950
1%
b101010 *
b10010 (
b10010 ,
#1960
0%
#1970
1%
b101011 *
b1111110 (
b1111110 ,
#1980
0%
#1990
1%
b101100 *
b1101101 (
b1101101 ,
#2000
0%
#2010
1%
b101101 *
b111001 (
b111001 ,
#2020
0%
#2030
1%
b101110 *
b11111 (
b11111 ,
#2040
0%
#2050
1%
b101111 *
b11010011 (
b11010011 ,
#2060
0%
#2070
1%
b110000 *
b10000101 (
b10000101 ,
#2080
0%
#2090
1%
b110001 *
b1111000 (
b1111000 ,
#2100
0%
#2110
1%
b110010 *
b1011011 (
b1011011 ,
#2120
0%
#2130
1%
b110011 *
b1001001 (
b1001001 ,
#2140
0%
#2150
1%
b110100 *
b111111 (
b111111 ,
#2160
0%
#2170
1%
b110101 *
b101010 (
b101010 ,
#2180
0%
#2190
1%
b110110 *
b1011000 (
b1011000 ,
#2200
0%
#2210
1%
b110111 *
b10000110 (
b10000110 ,
#2220
0%
#2230
1%
b111000 *
b10001110 (
b10001110 ,
#2240
0%
#2250
1%
b111001 *
b10011100 (
b10011100 ,
#2260
0%
#2270
1%
b111010 *
b11111010 (
b11111010 ,
#2280
0%
#2290
1%
b111011 *
b100110 (
b100110 ,
#2300
0%
#2310
1%
b111100 *
b1110011 (
b1110011 ,
#2320
0%
#2330
1%
b111101 *
b10100011 (
b10100011 ,
#2340
0%
#2350
1%
b111110 *
b101111 (
b101111 ,
#2360
0%
#2370
1%
b111111 *
b10110011 (
b10110011 ,
#2380
0%
#2390
1%
b1000000 *
b1011111 (
b1011111 ,
#2400
0%
#2410
1%
b1000001 *
b1000100 (
b1000100 ,
#2420
0%
#2430
1%
b1000010 *
b11110111 (
b11110111 ,
#2440
0%
#2450
1%
b1000011 *
b11001011 (
b11001011 ,
#2460
0%
#2470
1%
b1000100 *
b11100110 (
b11100110 ,
#2480
0%
#2490
1%
b1000101 *
b1011010 (
b1011010 ,
#2500
0%
#2510
1%
b1000110 *
b101001 (
b101001 ,
#2520
0%
#2530
1%
b1000111 *
b11101101 (
b11101101 ,
#2540
0%
#2550
1%
b1001000 *
b11011010 (
b11011010 ,
#2560
0%
#2570
1%
b1001001 *
b1100101 (
b1100101 ,
#2580
0%
#2590
1%
b1001010 *
b10110101 (
b10110101 ,
#2600
0%
#2610
1%
b1001011 *
b11011111 (
b11011111 ,
#2620
0%
#2630
1%
b1001100 *
b1111001 (
b1111001 ,
#2640
0%
#2650
1%
b1001101 *
b1000100 (
b1000100 ,
#2660
0%
#2670
1%
b1001110 *
b11010000 (
b11010000 ,
#2680
0%
#2690
1%
b1001111 *
b101010 (
b101010 ,
#2700
0%
#2710
1%
b1010000 *
b10101011 (
b10101011 ,
#2720
0%
#2730
1%
b1010001 *
b1110 (
b1110 ,
#2740
0%
#2750
1%
b1010010 *
b11011100 (
b11011100 ,
#2760
0%
#2770
1%
b1010011 *
b10011010 (
b10011010 ,
#2780
0%
#2790
1%
b1010100 *
b11111101 (
b11111101 ,
#2800
0%
#2810
1%
b1010101 *
b11000011 (
b11000011 ,
#2820
0%
#2830
1%
b1010110 *
b1010110 (
b1010110 ,
#2840
0%
#2850
1%
b1010111 *
b1001110 (
b1001110 ,
#2860
0%
#2870
1%
b1011000 *
b1100111 (
b1100111 ,
#2880
0%
#2890
1%
b1011001 *
b1010 (
b1010 ,
#2900
0%
#2910
1%
b1011010 *
b10110110 (
b10110110 ,
#2920
0%
#2930
1%
b1011011 *
b111000 (
b111000 ,
#2940
0%
#2950
1%
b1011100 *
b1111001 (
b1111001 ,
#2960
0%
#2970
1%
b1011101 *
b10111000 (
b10111000 ,
#2980
0%
#2990
1%
b1011110 *
b10010100 (
b10010100 ,
#3000
0%
#3010
1%
b1011111 *
b10010011 (
b10010011 ,
#3020
0%
#3030
1%
b1100000 *
b100 (
b100 ,
#3040
0%
#3050
1%
b1100001 *
b1011001 (
b1011001 ,
#3060
0%
#3070
1%
b1100010 *
b11011011 (
b11011011 ,
#3080
0%
#3090
1%
b1100011 *
b1001101 (
b1001101 ,
#3100
0%
#3110
1%
b1100100 *
b11011001 (
b11011001 ,
