sequential_circuits/d_flip_flop/best_d_flipflop.v
module d_flipflop(q, d, clk, preset, reset);
    input d, clk, preset, reset;
    output reg q;
    always @(negedge clk) begin
        if (reset) q <= 1'b0;
        else if (preset) q <= 1'b1;
        else q <= d;
    end
endmodule

sequential_circuits/d_flip_flop/best_d_flipflop_tb.v
`timescale 1ps/1ps
`include "best_d_flipflop.v"

module best_d_flip_flop_tb;
    reg d, clk, preset, reset;
    wire q;
    integer i;
    d_flipflop dff1(q, d, clk, preset, reset);

    initial begin
        clk = 0;
        for (i = 0; i<1000; i = i+1) begin
            #10 clk = ~clk;
        end
    end
    initial begin
        $dumpfile("best_d_flipflop.vcd");
        $dumpvars(0, dff1);
        d = 0; reset = 0; preset = 0;
        #30 d = 1;
        #30 d = 0;
        #30 d = 1;
        #30 reset = ~reset;
        #30 d = 0;
        #30 d = 1;
        #30 reset = ~reset;
        #30 d = 0;
        #30 d = 1;
        #30 d = 0;
        #30 d = 1;
        #30 preset = ~preset;
        #30 d = 0;
        #30 d = 1;
        #30 preset = ~preset;
        #30 d = 0;
    end
endmodule

sequential_circuits/d_flip_flop/best_d_flipflop.vcd
$date
	Fri Dec 22 01:09:47 2023
$end
$version
	Icarus Verilog
$end
$timescale
	1ps
$end
$scope module best_d_flip_flop_tb $end
$scope module dff1 $end
$var wire 1 ! clk $end
$var wire 1 " d $end
$var wire 1 # preset $end
$var wire 1 $ reset $end
$var reg 1 % q $end
$upscope $end
$upscope $end
$enddefinitions $end
$comment Show the parameter values. $end
$dumpall
$end
#0
$dumpvars
0%
0$
0#
0"
0!
$end
#10
1!
#20
0!
#30
1!
1"
#40
1%
0!
#50
1!
#60
0%
0!
0"
#70
1!
#80
0!
#90
1!
1"
#100
1%
0!
#110
1!
#120
0%
0!
1$
#130
1!
#140
0!
#150
1!
0"
#160
0!
#170
1!
#180
0!
1"
#190
1!
#200
0!
#210
1!
0$
#220
1%
0!
#230
1!
#240
0%
0!
0"
#250
1!
#260
0!
#270
1!
1"
#280
1%
0!
#290
1!
#300
0%
0!
0"
#310
1!
#320
0!
#330
1!
1"
#340
1%
0!
#350
1!
#360
0!
1#
#370
1!
#380
0!
#390
1!
0"
#400
0!
#410
1!
#420
0!
1"
#430
1!
#440
0!
#450
1!
0#
#460
0!
#470
1!
#480
0%
0!
0"
