combinational_circuits/basic_gates/and_gate.v
module and_gate(o, a, b);
    input a, b;
    output o;
    assign o = a & b;
endmodule

combinational_circuits/basic_gates/and_gate_testbench.v
`timescale 1ps/1ps
`include "and_gate.v"

module and_gate_testbench;
    reg a, b;
    wire o;
    integer i;
    and_gate a1(o, a, b);
    always #10 a = ~a;
    initial begin
        $dumpfile("edge_triggering.vcd");
        $dumpvars;
        a = 0; b = 1;
        #1
        for (i = 0; i < 1000; i = i+1) begin
            #10 b = ~b;
        end
        #1000 $stop;
    end
endmodule

combinational_circuits/basic_gates/edge_triggering.vcd
$date
	Mon Jan  1 16:56:07 2024
$end
$version
	Icarus Verilog
$end
$timescale
	1ps
$end
$scope module and_gate_testbench $end
$var wire 1 ! o $end
$var reg 1 " a $end
$var reg 1 # b $end
$var integer 32 $ i [31:0] $end
$scope module a1 $end
$var wire 1 " a $end
$var wire 1 # b $end
$var wire 1 ! o $end
$upscope $end
$upscope $end
$enddefinitions $end
$comment Show the parameter values. $end
$dumpall
$end
#0
$dumpvars
bx $
1#
0"
0!
$end
#1
b0 $
#10
1!
1"
#11
0!
b1 $
0#
#20
0"
#21
b10 $
1#
#30
1!
1"
#31
0!
b11 $
0#
#40
0"
#41
b100 $
1#
#50
1!
1"
#51
0!
b101 $
0#
#60
0"
#61
b110 $
1#
#70
1!
1"
#71
0!
b111 $
0#
#80
0"
#81
b1000 $
1#
#90
1!
1"
#91
0!
b1001 $
0#
#100
0"
#101
b1010 $
1#
#110
1!
1"
#111
0!
b1011 $
0#
#120
0"
#121
b1100 $
1#
#130
1!
1"
#131
0!
b1101 $
0#
#140
0"
#141
b1110 $
1#
#150
1!
1"
#151
0!
b1111 $
0#
#160
0"
#161
b10000 $
1#
#170
1!
1"
#171
0!
b10001 $
0#
#180
0"
#181
b10010 $
1#
#190
1!
1"
#191
0!
b10011 $
0#
#200
0"
#201
b10100 $
1#
#210
1!
1"
#211
0!
b10101 $
0#
#220
0"
#221
b10110 $
1#
#230
1!
1"
#231
0!
b10111 $
0#
#240
0"
#241
b11000 $
1#
#250
1!
1"
#251
0!
b11001 $
0#
#260
0"
#261
b11010 $
1#
#270
1!
1"
#271
0!
b11011 $
0#
#280
0"
#281
b11100 $
1#
#290
1!
1"
#291
0!
b11101 $
0#
#300
0"
#301
b11110 $
1#
#310
1!
1"
#311
0!
b11111 $
0#
#320
0"
#321
b100000 $
1#
#330
1!
1"
#331
0!
b100001 $
0#
#340
0"
#341
b100010 $
1#
#350
1!
1"
#351
0!
b100011 $
0#
#360
0"
#361
b100100 $
1#
#370
1!
1"
#371
0!
b100101 $
0#
#380
0"
#381
b100110 $
1#
#390
1!
1"
#391
0!
b100111 $
0#
#400
0"
#401
b101000 $
1#
#410
1!
1"
#411
0!
b101001 $
0#
#420
0"
#421
b101010 $
1#
#430
1!
1"
#431
0!
b101011 $
0#
#440
0"
#441
b101100 $
1#
#450
1!
1"
#451
0!
b101101 $
0#
#460
0"
#461
b101110 $
1#
#470
1!
1"
#471
0!
b101111 $
0#
#480
0"
#481
b110000 $
1#
#490
1!
1"
#491
0!
b110001 $
0#
#500
0"
#501
b110010 $
1#
#510
1!
1"
#511
0!
b110011 $
0#
#520
0"
#521
b110100 $
1#
#530
1!
1"
#531
0!
b110101 $
0#
#540
0"
#541
b110110 $
1#
#550
1!
1"
#551
0!
b110111 $
0#
#560
0"
#561
b111000 $
1#
#570
1!
1"
#571
0!
b111001 $
0#
#580
0"
#581
b111010 $
1#
#590
1!
1"
#591
0!
b111011 $
0#
#600
0"
#601
b111100 $
1#
#610
1!
1"
#611
0!
b111101 $
0#
#620
0"
#621
b111110 $
1#
#630
1!
1"
#631
0!
b111111 $
0#
#640
0"
#641
b1000000 $
1#
#650
1!
1"
#651
0!
b1000001 $
0#
#660
0"
#661
b1000010 $
1#
#670
1!
1"
#671
0!
b1000011 $
0#
#680
0"
#681
b1000100 $
1#
#690
1!
1"
#691
0!
b1000101 $
0#
#700
0"
#701
b1000110 $
1#
#710
1!
1"
#711
0!
b1000111 $
0#
#720
0"
#721
b1001000 $
1#
#730
1!
1"
#731
0!
b1001001 $
0#
#740
0"
#741
b1001010 $
1#
#750
1!
1"
#751
0!
b1001011 $
0#
#760
0"
#761
b1001100 $
1#
#770
1!
1"
#771
0!
b1001101 $
0#
#780
0"
#781
b1001110 $
1#
#790
1!
1"
#791
0!
b1001111 $
0#
#800
0"
#801
b1010000 $
1#
#810
1!
1"
#811
0!
b1010001 $
0#
#820
0"
#821
b1010010 $
1#
#830
1!
1"
#831
0!
b1010011 $
0#
#840
0"
#841
b1010100 $
1#
#850
1!
1"
#851
0!
b1010101 $
0#
#860
0"
#861
b1010110 $
1#
#870
1!
1"
#871
0!
b1010111 $
0#
#880
0"
#881
b1011000 $
1#
#890
1!
1"
#891
0!
b1011001 $
0#
#900
0"
#901
b1011010 $
1#
#910
1!
1"
#911
0!
b1011011 $
0#
#920
0"
#921
b1011100 $
1#
#930
1!
1"
#931
0!
b1011101 $
0#
#940
0"
#941
b1011110 $
1#
#950
1!
1"
#951
0!
b1011111 $
0#
#960
0"
#961
b1100000 $
1#
#970
1!
1"
#971
0!
b1100001 $
0#
#980
0"
#981
b1100010 $
1#
#990
1!
1"
#991
0!
b1100011 $
0#
#1000
0"
#1001
b1100100 $
1#
#1010
1!
1"
#1011
0!
b1100101 $
0#
#1020
0"
#1021
b1100110 $
1#
#1030
1!
1"
#1031
0!
b1100111 $
0#
#1040
0"
#1041
b1101000 $
1#
#1050
1!
1"
#1051
0!
b1101001 $
0#
#1060
0"
#1061
b1101010 $
1#
#1070
1!
1"
#1071
0!
b1101011 $
0#
#1080
0"
#1081
b1101100 $
1#
#1090
1!
1"
#1091
0!
b1101101 $
0#
#1100
0"
#1101
b1101110 $
1#
#1110
1!
1"
#1111
0!
b1101111 $
0#
#1120
0"
#1121
b1110000 $
1#
#1130
1!
1"
#1131
0!
b1110001 $
0#
#1140
0"
#1141
b1110010 $
1#
#1150
1!
1"
#1151
0!
b1110011 $
0#
#1160
0"
#1161
b1110100 $
1#
#1170
1!
1"
#1171
0!
b1110101 $
0#
#1180
0"
#1181
b1110110 $
1#
#1190
1!
1"
#1191
0!
b1110111 $
0#
#1200
0"
#1201
b1111000 $
1#
#1210
1!
1"
#1211
0!
b1111001 $
0#
#1220
0"
#1221
b1111010 $
1#
#1230
1!
1"
#1231
0!
b1111011 $
0#
#1240
0"
#1241
b1111100 $
1#
#1250
1!
1"
#1251
0!
b1111101 $
0#
#1260
0"
#1261
b1111110 $
1#
#1270
1!
1"
#1271
0!
b1111111 $
0#
#1280
0"
#1281
b10000000 $
1#
#1290
1!
1"
#1291
0!
b10000001 $
0#
#1300
0"
#1301
b10000010 $
1#
#1310
1!
1"
#1311
0!
b10000011 $
0#
#1320
0"
#1321
b10000100 $
1#
#1330
1!
1"
#1331
0!
b10000101 $
0#
#1340
0"
#1341
b10000110 $
1#
#1350
1!
1"
#1351
0!
b10000111 $
0#
#1360
0"
#1361
b10001000 $
1#
#1370
1!
1"
#1371
0!
b10001001 $
0#
#1380
0"
#1381
b10001010 $
1#
#1390
1!
1"
#1391
0!
b10001011 $
0#
#1400
0"
#1401
b10001100 $
1#
#1410
1!
1"
#1411
0!
b10001101 $
0#
#1420
0"
#1421
b10001110 $
1#
#1430
1!
1"
#1431
0!
b10001111 $
0#
#1440
0"
#1441
b10010000 $
1#
#1450
1!
1"
#1451
0!
b10010001 $
0#
#1460
0"
#1461
b10010010 $
1#
#1470
1!
1"
#1471
0!
b10010011 $
0#
#1480
0"
#1481
b10010100 $
1#
#1490
1!
1"
#1491
0!
b10010101 $
0#
#1500
0"
#1501
b10010110 $
1#
#1510
1!
1"
#1511
0!
b10010111 $
0#
#1520
0"
#1521
b10011000 $
1#
#1530
1!
1"
#1531
0!
b10011001 $
0#
#1540
0"
#1541
b10011010 $
1#
#1550
1!
1"
#1551
0!
b10011011 $
0#
#1560
0"
#1561
b10011100 $
1#
#1570
1!
1"
#1571
0!
b10011101 $
0#
#1580
0"
#1581
b10011110 $
1#
#1590
1!
1"
#1591
0!
b10011111 $
0#
#1600
0"
#1601
b10100000 $
1#
#1610
1!
1"
#1611
0!
b10100001 $
0#
#1620
0"
#1621
b10100010 $
1#
#1630
1!
1"
#1631
0!
b10100011 $
0#
#1640
0"
#1641
b10100100 $
1#
#1650
1!
1"
#1651
0!
b10100101 $
0#
#1660
0"
#1661
b10100110 $
1#
#1670
1!
1"
#1671
0!
b10100111 $
0#
#1680
0"
#1681
b10101000 $
1#
#1690
1!
1"
#1691
0!
b10101001 $
0#
#1700
0"
#1701
b10101010 $
1#
#1710
1!
1"
#1711
0!
b10101011 $
0#
#1720
0"
#1721
b10101100 $
1#
#1730
1!
1"
#1731
0!
b10101101 $
0#
#1740
0"
#1741
b10101110 $
1#
#1750
1!
1"
#1751
0!
b10101111 $
0#
#1760
0"
#1761
b10110000 $
1#
#1770
1!
1"
#1771
0!
b10110001 $
0#
#1780
0"
#1781
b10110010 $
1#
#1790
1!
1"
#1791
0!
b10110011 $
0#
#1800
0"
#1801
b10110100 $
1#
#1810
1!
1"
#1811
0!
b10110101 $
0#
#1820
0"
#1821
b10110110 $
1#
#1830
1!
1"
#1831
0!
b10110111 $
0#
#1840
0"
#1841
b10111000 $
1#
#1850
1!
1"
#1851
0!
b10111001 $
0#
#1860
0"
#1861
b10111010 $
1#
#1870
1!
1"
#1871
0!
b10111011 $
0#
#1880
0"
#1881
b10111100 $
1#
#1890
1!
1"
#1891
0!
b10111101 $
0#
#1900
0"
#1901
b10111110 $
1#
#1910
1!
1"
#1911
0!
b10111111 $
0#
#1920
0"
#1921
b11000000 $
1#
#1930
1!
1"
#1931
0!
b11000001 $
0#
#1940
0"
#1941
b11000010 $
1#
#1950
1!
1"
#1951
0!
b11000011 $
0#
#1960
0"
#1961
b11000100 $
1#
#1970
1!
1"
#1971
0!
b11000101 $
0#
#1980
0"
#1981
b11000110 $
1#
#1990
1!
1"
#1991
0!
b11000111 $
0#
#2000
0"
#2001
b11001000 $
1#
#2010
1!
1"
#2011
0!
b11001001 $
0#
#2020
0"
#2021
b11001010 $
1#
#2030
1!
1"
#2031
0!
b11001011 $
0#
#2040
0"
#2041
b11001100 $
1#
#2050
1!
1"
#2051
0!
b11001101 $
0#
#2060
0"
#2061
b11001110 $
1#
#2070
1!
1"
#2071
0!
b11001111 $
0#
#2080
0"
#2081
b11010000 $
1#
#2090
1!
1"
#2091
0!
b11010001 $
0#
#2100
0"
#2101
b11010010 $
1#
#2110
1!
1"
#2111
0!
b11010011 $
0#
#2120
0"
#2121
b11010100 $
1#
#2130
1!
1"
#2131
0!
b11010101 $
0#
#2140
0"
#2141
b11010110 $
1#
#2150
1!
1"
#2151
0!
b11010111 $
0#
#2160
0"
#2161
b11011000 $
1#
#2170
1!
1"
#2171
0!
b11011001 $
0#
#2180
0"
#2181
b11011010 $
1#
#2190
1!
1"
#2191
0!
b11011011 $
0#
#2200
0"
#2201
b11011100 $
1#
#2210
1!
1"
#2211
0!
b11011101 $
0#
#2220
0"
#2221
b11011110 $
1#
#2230
1!
1"
#2231
0!
b11011111 $
0#
#2240
0"
#2241
b11100000 $
1#
#2250
1!
1"
#2251
0!
b11100001 $
0#
#2260
0"
#2261
b11100010 $
1#
#2270
1!
1"
#2271
0!
b11100011 $
0#
#2280
0"
#2281
b11100100 $
1#
#2290
1!
1"
#2291
0!
b11100101 $
0#
#2300
0"
#2301
b11100110 $
1#
#2310
1!
1"
#2311
0!
b11100111 $
0#
#2320
0"
#2321
b11101000 $
1#
#2330
1!
1"
#2331
0!
b11101001 $
0#
#2340
0"
#2341
b11101010 $
1#
#2350
1!
1"
#2351
0!
b11101011 $
0#
#2360
0"
#2361
b11101100 $
1#
#2370
1!
1"
#2371
0!
b11101101 $
0#
#2380
0"
#2381
b11101110 $
1#
#2390
1!
1"
#2391
0!
b11101111 $
0#
#2400
0"
#2401
b11110000 $
1#
#2410
1!
1"
#2411
0!
b11110001 $
0#
#2420
0"
#2421
b11110010 $
1#
#2430
1!
1"
#2431
0!
b11110011 $
0#
#2440
0"
#2441
b11110100 $
1#
#2450
1!
1"
#2451
0!
b11110101 $
0#
#2460
0"
#2461
b11110110 $
1#
#2470
1!
1"
#2471
0!
b11110111 $
0#
#2480
0"
#2481
b11111000 $
1#
#2490
1!
1"
#2491
0!
b11111001 $
0#
#2500
0"
#2501
b11111010 $
1#
#2510
1!
1"
#2511
0!
b11111011 $
0#
#2520
0"
#2521
b11111100 $
1#
#2530
1!
1"
#2531
0!
b11111101 $
0#
#2540
0"
#2541
b11111110 $
1#
#2550
1!
1"
#2551
0!
b11111111 $
0#
#2560
0"
#2561
b100000000 $
1#
#2570
1!
1"
#2571
0!
b100000001 $
0#
#2580
0"
#2581
b100000010 $
1#
#2590
1!
1"
#2591
0!
b100000011 $
0#
#2600
0"
#2601
b100000100 $
1#
#2610
1!
1"
#2611
0!
b100000101 $
0#
#2620
0"
#2621
b100000110 $
1#
#2630
1!
1"
#2631
0!
b100000111 $
0#
#2640
0"
#2641
b100001000 $
1#
#2650
1!
1"
#2651
0!
b100001001 $
0#
#2660
0"
#2661
b100001010 $
1#
#2670
1!
1"
#2671
0!
b100001011 $
0#
#2680
0"
#2681
b100001100 $
1#
#2690
1!
1"
#2691
0!
b100001101 $
0#
#2700
0"
#2701
b100001110 $
1#
#2710
1!
1"
#2711
0!
b100001111 $
0#
#2720
0"
#2721
b100010000 $
1#
#2730
1!
1"
#2731
0!
b100010001 $
0#
#2740
0"
#2741
b100010010 $
1#
#2750
1!
1"
#2751
0!
b100010011 $
0#
#2760
0"
#2761
b100010100 $
1#
#2770
1!
1"
#2771
0!
b100010101 $
0#
#2780
0"
#2781
b100010110 $
1#
#2790
1!
1"
#2791
0!
b100010111 $
0#
#2800
0"
#2801
b100011000 $
1#
#2810
1!
1"
#2811
0!
b100011001 $
0#
#2820
0"
#2821
b100011010 $
1#
#2830
1!
1"
#2831
0!
b100011011 $
0#
#2840
0"
#2841
b100011100 $
1#
#2850
1!
1"
#2851
0!
b100011101 $
0#
#2860
0"
#2861
b100011110 $
1#
#2870
1!
1"
#2871
0!
b100011111 $
0#
#2880
0"
#2881
b100100000 $
1#
#2890
1!
1"
#2891
0!
b100100001 $
0#
#2900
0"
#2901
b100100010 $
1#
#2910
1!
1"
#2911
0!
b100100011 $
0#
#2920
0"
#2921
b100100100 $
1#
#2930
1!
1"
#2931
0!
b100100101 $
0#
#2940
0"
#2941
b100100110 $
1#
#2950
1!
1"
#2951
0!
b100100111 $
0#
#2960
0"
#2961
b100101000 $
1#
#2970
1!
1"
#2971
0!
b100101001 $
0#
#2980
0"
#2981
b100101010 $
1#
#2990
1!
1"
#2991
0!
b100101011 $
0#
#3000
0"
#3001
b100101100 $
1#
#3010
1!
1"
#3011
0!
b100101101 $
0#
#3020
0"
#3021
b100101110 $
1#
#3030
1!
1"
#3031
0!
b100101111 $
0#
#3040
0"
#3041
b100110000 $
1#
#3050
1!
1"
#3051
0!
b100110001 $
0#
#3060
0"
#3061
b100110010 $
1#
#3070
1!
1"
#3071
0!
b100110011 $
0#
#3080
0"
#3081
b100110100 $
1#
#3090
1!
1"
#3091
0!
b100110101 $
0#
#3100
0"
#3101
b100110110 $
1#
#3110
1!
1"
#3111
0!
b100110111 $
0#
#3120
0"
#3121
b100111000 $
1#
#3130
1!
1"
#3131
0!
b100111001 $
0#
#3140
0"
#3141
b100111010 $
1#
#3150
1!
1"
#3151
0!
b100111011 $
0#
#3160
0"
#3161
b100111100 $
1#
#3170
1!
1"
#3171
0!
b100111101 $
0#
#3180
0"
#3181
b100111110 $
1#
#3190
1!
1"
#3191
0!
b100111111 $
0#
#3200
0"
#3201
b101000000 $
1#
#3210
1!
1"
#3211
0!
b101000001 $
0#
#3220
0"
#3221
b101000010 $
1#
#3230
1!
1"
#3231
0!
b101000011 $
0#
#3240
0"
#3241
b101000100 $
1#
#3250
1!
1"
#3251
0!
b101000101 $
0#
#3260
0"
#3261
b101000110 $
1#
#3270
1!
1"
#3271
0!
b101000111 $
0#
#3280
0"
#3281
b101001000 $
1#
#3290
1!
1"
#3291
0!
b101001001 $
0#
#3300
0"
#3301
b101001010 $
1#
#3310
1!
1"
#3311
0!
b101001011 $
0#
#3320
0"
#3321
b101001100 $
1#
#3330
1!
1"
#3331
0!
b101001101 $
0#
#3340
0"
#3341
b101001110 $
1#
#3350
1!
1"
#3351
0!
b101001111 $
0#
#3360
0"
#3361
b101010000 $
1#
#3370
1!
1"
#3371
0!
b101010001 $
0#
#3380
0"
#3381
b101010010 $
1#
#3390
1!
1"
#3391
0!
b101010011 $
0#
#3400
0"
#3401
b101010100 $
1#
#3410
1!
1"
#3411
0!
b101010101 $
0#
#3420
0"
#3421
b101010110 $
1#
#3430
1!
1"
#3431
0!
b101010111 $
0#
#3440
0"
#3441
b101011000 $
1#
#3450
1!
1"
#3451
0!
b101011001 $
0#
#3460
0"
#3461
b101011010 $
1#
#3470
1!
1"
#3471
0!
b101011011 $
0#
#3480
0"
#3481
b101011100 $
1#
#3490
1!
1"
#3491
0!
b101011101 $
0#
#3500
0"
#3501
b101011110 $
1#
#3510
1!
1"
#3511
0!
b101011111 $
0#
#3520
0"
#3521
b101100000 $
1#
#3530
1!
1"
#3531
0!
b101100001 $
0#
#3540
0"
#3541
b101100010 $
1#
#3550
1!
1"
#3551
0!
b101100011 $
0#
#3560
0"
#3561
b101100100 $
1#
#3570
1!
1"
#3571
0!
b101100101 $
0#
#3580
0"
#3581
b101100110 $
1#
#3590
1!
1"
#3591
0!
b101100111 $
0#
#3600
0"
#3601
b101101000 $
1#
#3610
1!
1"
#3611
0!
b101101001 $
0#
#3620
0"
#3621
b101101010 $
1#
#3630
1!
1"
#3631
0!
b101101011 $
0#
#3640
0"
#3641
b101101100 $
1#
#3650
1!
1"
#3651
0!
b101101101 $
0#
#3660
0"
#3661
b101101110 $
1#
#3670
1!
1"
#3671
0!
b101101111 $
0#
#3680
0"
#3681
b101110000 $
1#
#3690
1!
1"
#3691
0!
b101110001 $
0#
#3700
0"
#3701
b101110010 $
1#
#3710
1!
1"
#3711
0!
b101110011 $
0#
#3720
0"
#3721
b101110100 $
1#
#3730
1!
1"
#3731
0!
b101110101 $
0#
#3740
0"
#3741
b101110110 $
1#
#3750
1!
1"
#3751
0!
b101110111 $
0#
#3760
0"
#3761
b101111000 $
1#
#3770
1!
1"
#3771
0!
b101111001 $
0#
#3780
0"
#3781
b101111010 $
1#
#3790
1!
1"
#3791
0!
b101111011 $
0#
#3800
0"
#3801
b101111100 $
1#
#3810
1!
1"
#3811
0!
b101111101 $
0#
#3820
0"
#3821
b101111110 $
1#
#3830
1!
1"
#3831
0!
b101111111 $
0#
#3840
0"
#3841
b110000000 $
1#
#3850
1!
1"
#3851
0!
b110000001 $
0#
#3860
0"
#3861
b110000010 $
1#
#3870
1!
1"
#3871
0!
b110000011 $
0#
#3880
0"
#3881
b110000100 $
1#
#3890
1!
1"
#3891
0!
b110000101 $
0#
#3900
0"
#3901
b110000110 $
1#
#3910
1!
1"
#3911
0!
b110000111 $
0#
#3920
0"
#3921
b110001000 $
1#
#3930
1!
1"
#3931
0!
b110001001 $
0#
#3940
0"
#3941
b110001010 $
1#
#3950
1!
1"
#3951
0!
b110001011 $
0#
#3960
0"
#3961
b110001100 $
1#
#3970
1!
1"
#3971
0!
b110001101 $
0#
#3980
0"
#3981
b110001110 $
1#
#3990
1!
1"
#3991
0!
b110001111 $
0#
#4000
0"
#4001
b110010000 $
1#
#4010
1!
1"
#4011
0!
b110010001 $
0#
#4020
0"
#4021
b110010010 $
1#
#4030
1!
1"
#4031
0!
b110010011 $
0#
#4040
0"
#4041
b110010100 $
1#
#4050
1!
1"
#4051
0!
b110010101 $
0#
#4060
0"
#4061
b110010110 $
1#
#4070
1!
1"
#4071
0!
b110010111 $
0#
#4080
0"
#4081
b110011000 $
1#
#4090
1!
1"
#4091
0!
b110011001 $
0#
#4100
0"
#4101
b110011010 $
1#
#4110
1!
1"
#4111
0!
b110011011 $
0#
#4120
0"
#4121
b110011100 $
1#
#4130
1!
1"
#4131
0!
b110011101 $
0#
#4140
0"
#4141
b110011110 $
1#
#4150
1!
1"
#4151
0!
b110011111 $
0#
#4160
0"
#4161
b110100000 $
1#
#4170
1!
1"
#4171
0!
b110100001 $
0#
#4180
0"
#4181
b110100010 $
1#
#4190
1!
1"
#4191
0!
b110100011 $
0#
#4200
0"
#4201
b110100100 $
1#
#4210
1!
1"
#4211
0!
b110100101 $
0#
#4220
0"
#4221
b110100110 $
1#
#4230
1!
1"
#4231
0!
b110100111 $
0#
#4240
0"
#4241
b110101000 $
1#
#4250
1!
1"
#4251
0!
b110101001 $
0#
#4260
0"
#4261
b110101010 $
1#
#4270
1!
1"
#4271
0!
b110101011 $
0#
#4280
0"
#4281
b110101100 $
1#
#4290
1!
1"
#4291
0!
b110101101 $
0#
#4300
0"
#4301
b110101110 $
1#
#4310
1!
1"
#4311
0!
b110101111 $
0#
#4320
0"
#4321
b110110000 $
1#
#4330
1!
1"
#4331
0!
b110110001 $
0#
#4340
0"
#4341
b110110010 $
1#
#4350
1!
1"
#4351
0!
b110110011 $
0#
#4360
0"
#4361
b110110100 $
1#
#4370
1!
1"
#4371
0!
b110110101 $
0#
#4380
0"
#4381
b110110110 $
1#
#4390
1!
1"
#4391
0!
b110110111 $
0#
#4400
0"
#4401
b110111000 $
1#
#4410
1!
1"
#4411
0!
b110111001 $
0#
#4420
0"
#4421
b110111010 $
1#
#4430
1!
1"
#4431
0!
b110111011 $
0#
#4440
0"
#4441
b110111100 $
1#
#4450
1!
1"
#4451
0!
b110111101 $
0#
#4460
0"
#4461
b110111110 $
1#
#4470
1!
1"
#4471
0!
b110111111 $
0#
#4480
0"
#4481
b111000000 $
1#
#4490
1!
1"
#4491
0!
b111000001 $
0#
#4500
0"
#4501
b111000010 $
1#
#4510
1!
1"
#4511
0!
b111000011 $
0#
#4520
0"
#4521
b111000100 $
1#
#4530
1!
1"
#4531
0!
b111000101 $
0#
#4540
0"
#4541
b111000110 $
1#
#4550
1!
1"
#4551
0!
b111000111 $
0#
#4560
0"
#4561
b111001000 $
1#
#4570
1!
1"
#4571
0!
b111001001 $
0#
#4580
0"
#4581
b111001010 $
1#
#4590
1!
1"
#4591
0!
b111001011 $
0#
#4600
0"
#4601
b111001100 $
1#
#4610
1!
1"
#4611
0!
b111001101 $
0#
#4620
0"
#4621
b111001110 $
1#
#4630
1!
1"
#4631
0!
b111001111 $
0#
#4640
0"
#4641
b111010000 $
1#
#4650
1!
1"
#4651
0!
b111010001 $
0#
#4660
0"
#4661
b111010010 $
1#
#4670
1!
1"
#4671
0!
b111010011 $
0#
#4680
0"
#4681
b111010100 $
1#
#4690
1!
1"
#4691
0!
b111010101 $
0#
#4700
0"
#4701
b111010110 $
1#
#4710
1!
1"
#4711
0!
b111010111 $
0#
#4720
0"
#4721
b111011000 $
1#
#4730
1!
1"
#4731
0!
b111011001 $
0#
#4740
0"
#4741
b111011010 $
1#
#4750
1!
1"
#4751
0!
b111011011 $
0#
#4760
0"
#4761
b111011100 $
1#
#4770
1!
1"
#4771
0!
b111011101 $
0#
#4780
0"
#4781
b111011110 $
1#
#4790
1!
1"
#4791
0!
b111011111 $
0#
#4800
0"
#4801
b111100000 $
1#
#4810
1!
1"
#4811
0!
b111100001 $
0#
#4820
0"
#4821
b111100010 $
1#
#4830
1!
1"
#4831
0!
b111100011 $
0#
#4840
0"
#4841
b111100100 $
1#
#4850
1!
1"
#4851
0!
b111100101 $
0#
#4860
0"
#4861
b111100110 $
1#
#4870
1!
1"
#4871
0!
b111100111 $
0#
#4880
0"
#4881
b111101000 $
1#
#4890
1!
1"
#4891
0!
b111101001 $
0#
#4900
0"
#4901
b111101010 $
1#
#4910
1!
1"
#4911
0!
b111101011 $
0#
#4920
0"
#4921
b111101100 $
1#
#4930
1!
1"
#4931
0!
b111101101 $
0#
#4940
0"
#4941
b111101110 $
1#
#4950
1!
1"
#4951
0!
b111101111 $
0#
#4960
0"
#4961
b111110000 $
1#
#4970
1!
1"
#4971
0!
b111110001 $
0#
#4980
0"
#4981
b111110010 $
1#
#4990
1!
1"
#4991
0!
b111110011 $
0#
#5000
0"
#5001
b111110100 $
1#
#5010
1!
1"
#5011
0!
b111110101 $
0#
#5020
0"
#5021
b111110110 $
1#
#5030
1!
1"
#5031
0!
b111110111 $
0#
#5040
0"
#5041
b111111000 $
1#
#5050
1!
1"
#5051
0!
b111111001 $
0#
#5060
0"
#5061
b111111010 $
1#
#5070
1!
1"
#5071
0!
b111111011 $
0#
#5080
0"
#5081
b111111100 $
1#
#5090
1!
1"
#5091
0!
b111111101 $
0#
#5100
0"
#5101
b111111110 $
1#
#5110
1!
1"
#5111
0!
b111111111 $
0#
#5120
0"
#5121
b1000000000 $
1#
#5130
1!
1"
#5131
0!
b1000000001 $
0#
#5140
0"
#5141
b1000000010 $
1#
#5150
1!
1"
#5151
0!
b1000000011 $
0#
#5160
0"
#5161
b1000000100 $
1#
#5170
1!
1"
#5171
0!
b1000000101 $
0#
#5180
0"
#5181
b1000000110 $
1#
#5190
1!
1"
#5191
0!
b1000000111 $
0#
#5200
0"
#5201
b1000001000 $
1#
#5210
1!
1"
#5211
0!
b1000001001 $
0#
#5220
0"
#5221
b1000001010 $
1#
#5230
1!
1"
#5231
0!
b1000001011 $
0#
#5240
0"
#5241
b1000001100 $
1#
#5250
1!
1"
#5251
0!
b1000001101 $
0#
#5260
0"
#5261
b1000001110 $
1#
#5270
1!
1"
#5271
0!
b1000001111 $
0#
#5280
0"
#5281
b1000010000 $
1#
#5290
1!
1"
#5291
0!
b1000010001 $
0#
#5300
0"
#5301
b1000010010 $
1#
#5310
1!
1"
#5311
0!
b1000010011 $
0#
#5320
0"
#5321
b1000010100 $
1#
#5330
1!
1"
#5331
0!
b1000010101 $
0#
#5340
0"
#5341
b1000010110 $
1#
#5350
1!
1"
#5351
0!
b1000010111 $
0#
#5360
0"
#5361
b1000011000 $
1#
#5370
1!
1"
#5371
0!
b1000011001 $
0#
#5380
0"
#5381
b1000011010 $
1#
#5390
1!
1"
#5391
0!
b1000011011 $
0#
#5400
0"
#5401
b1000011100 $
1#
#5410
1!
1"
#5411
0!
b1000011101 $
0#
#5420
0"
#5421
b1000011110 $
1#
#5430
1!
1"
#5431
0!
b1000011111 $
0#
#5440
0"
#5441
b1000100000 $
1#
#5450
1!
1"
#5451
0!
b1000100001 $
0#
#5460
0"
#5461
b1000100010 $
1#
#5470
1!
1"
#5471
0!
b1000100011 $
0#
#5480
0"
#5481
b1000100100 $
1#
#5490
1!
1"
#5491
0!
b1000100101 $
0#
#5500
0"
#5501
b1000100110 $
1#
#5510
1!
1"
#5511
0!
b1000100111 $
0#
#5520
0"
#5521
b1000101000 $
1#
#5530
1!
1"
#5531
0!
b1000101001 $
0#
#5540
0"
#5541
b1000101010 $
1#
#5550
1!
1"
#5551
0!
b1000101011 $
0#
#5560
0"
#5561
b1000101100 $
1#
#5570
1!
1"
#5571
0!
b1000101101 $
0#
#5580
0"
#5581
b1000101110 $
1#
#5590
1!
1"
#5591
0!
b1000101111 $
0#
#5600
0"
#5601
b1000110000 $
1#
#5610
1!
1"
#5611
0!
b1000110001 $
0#
#5620
0"
#5621
b1000110010 $
1#
#5630
1!
1"
#5631
0!
b1000110011 $
0#
#5640
0"
#5641
b1000110100 $
1#
#5650
1!
1"
#5651
0!
b1000110101 $
0#
#5660
0"
#5661
b1000110110 $
1#
#5670
1!
1"
#5671
0!
b1000110111 $
0#
#5680
0"
#5681
b1000111000 $
1#
#5690
1!
1"
#5691
0!
b1000111001 $
0#
#5700
0"
#5701
b1000111010 $
1#
#5710
1!
1"
#5711
0!
b1000111011 $
0#
#5720
0"
#5721
b1000111100 $
1#
#5730
1!
1"
#5731
0!
b1000111101 $
0#
#5740
0"
#5741
b1000111110 $
1#
#5750
1!
1"
#5751
0!
b1000111111 $
0#
#5760
0"
#5761
b1001000000 $
1#
#5770
1!
1"
#5771
0!
b1001000001 $
0#
#5780
0"
#5781
b1001000010 $
1#
#5790
1!
1"
#5791
0!
b1001000011 $
0#
#5800
0"
#5801
b1001000100 $
1#
#5810
1!
1"
#5811
0!
b1001000101 $
0#
#5820
0"
#5821
b1001000110 $
1#
#5830
1!
1"
#5831
0!
b1001000111 $
0#
#5840
0"
#5841
b1001001000 $
1#
#5850
1!
1"
#5851
0!
b1001001001 $
0#
#5860
0"
#5861
b1001001010 $
1#
#5870
1!
1"
#5871
0!
b1001001011 $
0#
#5880
0"
#5881
b1001001100 $
1#
#5890
1!
1"
#5891
0!
b1001001101 $
0#
#5900
0"
#5901
b1001001110 $
1#
#5910
1!
1"
#5911
0!
b1001001111 $
0#
#5920
0"
#5921
b1001010000 $
1#
#5930
1!
1"
#5931
0!
b1001010001 $
0#
#5940
0"
#5941
b1001010010 $
1#
#5950
1!
1"
#5951
0!
b1001010011 $
0#
#5960
0"
#5961
b1001010100 $
1#
#5970
1!
1"
#5971
0!
b1001010101 $
0#
#5980
0"
#5981
b1001010110 $
1#
#5990
1!
1"
#5991
0!
b1001010111 $
0#
#6000
0"
#6001
b1001011000 $
1#
#6010
1!
1"
#6011
0!
b1001011001 $
0#
#6020
0"
#6021
b1001011010 $
1#
#6030
1!
1"
#6031
0!
b1001011011 $
0#
#6040
0"
#6041
b1001011100 $
1#
#6050
1!
1"
#6051
0!
b1001011101 $
0#
#6060
0"
#6061
b1001011110 $
1#
#6070
1!
1"
#6071
0!
b1001011111 $
0#
#6080
0"
#6081
b1001100000 $
1#
#6090
1!
1"
#6091
0!
b1001100001 $
0#
