combinational_circuits/Practice 0/full_adder.v
module full_adder(a, b, c, sum, carry);
    input a, b, c;
    output sum, carry;

    xor x1(temp1, a, b);
    and a1(temp2, a, b);
    xor x2(sum, temp1, c);
    and a2(temp3, temp1, c);
    or o1(carry, temp2, temp3);

endmodule

combinational_circuits/Practice 0/full_adder_tb.v
`include "full_adder.v"

module full_adder_tb;
    reg a,b,c;
    wire sum, carry;

    full_adder add1(a, b, c, sum, carry);

    initial begin
        $dumpfile("full_adder.vcd");
        $dumpvars(0, full_adder_tb);
        
        a=0; b=0; c=0;
        #1
        a=0; b=0; c=1;
        #1
        a=0; b=1; c=0;
        #1
        a=0; b=1; c=1;
        #1
        a=1; b=0; c=0;
        #1
        a=1; b=0; c=1;
        #1
        a=1; b=1; c=0;
        #1
        a=1; b=1; c=1;
        #1
        a=1; b=1; c=1;
    end


endmodule

combinational_circuits/Practice 0/full_adder.vcd
$date
	Tue Oct 24 21:24:19 2023
$end
$version
	Icarus Verilog
$end
$timescale
	1s
$end
$scope module full_adder_tb $end
$var wire 1 ! sum $end
$var wire 1 " carry $end
$var reg 1 # a $end
$var reg 1 $ b $end
$var reg 1 % c $end
$scope module add1 $end
$var wire 1 # a $end
$var wire 1 $ b $end
$var wire 1 % c $end
$var wire 1 " carry $end
$var wire 1 ! sum $end
$var wire 1 & temp1 $end
$var wire 1 ' temp2 $end
$var wire 1 ( temp3 $end
$upscope $end
$upscope $end
$enddefinitions $end
$comment Show the parameter values. $end
$dumpall
$end
#0
$dumpvars
0(
0'
0&
0%
0$
0#
0"
0!
$end
#1
1!
1%
#2
1&
0%
1$
#3
1"
0!
1(
1%
#4
0"
1!
0(
0%
0$
1#
#5
1"
0!
1(
1%
#6
0(
0&
1'
0%
1$
#7
1!
1%
