sequential_circuits/ram/single_port_ram.v
module single_port_ram(rd_data, wr_data, wr_en, wr_addr, rd_addr, clk);
    input clk, wr_en;
    input [7:0] wr_data;
    input [9:0] wr_addr, rd_addr;
    output [7:0] rd_data;


    reg[7:0] rd_data2;
    reg [7:0] ram_memory[0:1023];

    always @(posedge clk) begin
        if (wr_en) ram_memory[wr_addr] <= wr_data;
        rd_data2 <= ram_memory[rd_addr];
    end

    assign rd_data = rd_data2;
endmodule

sequential_circuits/ram/single_port_ram_tb.v
`timescale 1ps/1ps
`include "single_port_ram.v"

module single_port_ram_tb;
    reg clk, wr_en;
    reg [7:0] wr_data;
    reg [9:0] wr_addr, rd_addr;
    wire [7:0] rd_data;

    integer i;

    single_port_ram spr1(rd_data, wr_data, wr_en, wr_addr, rd_addr, clk);

    always #10 clk = ~clk;

    initial begin
        clk = 0; wr_en = 0; wr_data = 0; wr_addr = 0; rd_addr = 0;
        #10
        #20 wr_en = 1; wr_data = 8'd80; wr_addr = 10'd80; rd_addr = 10'd80;
        #20 wr_addr = 10'd0; wr_data = 8'd90;
        #20 wr_addr = 10'd80;
        #20 wr_addr = 10'd1023; rd_addr = 10'd0;
        #20 rd_addr = 10'd80;
        #20 rd_addr = 10'd1000;
        #20 rd_addr = 10'd1023;
    end

    initial begin
        $dumpfile ("single_port_ram.vcd");
        $dumpvars;
        $monitor("time = %d \t rd_addr = %d \t rd_data = %d", $time, rd_addr, rd_data);
        #1000 $finish;
    end
endmodule

sequential_circuits/ram/single_port_ram.vcd
$date
	Sun Jan  7 23:12:32 2024
$end
$version
	Icarus Verilog
$end
$timescale
	1ps
$end
$scope module single_port_ram_tb $end
$var wire 8 ! rd_data [7:0] $end
$var reg 1 " clk $end
$var reg 10 # rd_addr [9:0] $end
$var reg 10 $ wr_addr [9:0] $end
$var reg 8 % wr_data [7:0] $end
$var reg 1 & wr_en $end
$scope module spr1 $end
$var wire 1 " clk $end
$var wire 10 ' rd_addr [9:0] $end
$var wire 8 ( rd_data [7:0] $end
$var wire 10 ) wr_addr [9:0] $end
$var wire 8 * wr_data [7:0] $end
$var wire 1 & wr_en $end
$var reg 8 + rd_data2 [7:0] $end
$upscope $end
$upscope $end
$enddefinitions $end
$comment Show the parameter values. $end
$dumpall
$end
#0
$dumpvars
bx +
b0 *
b0 )
bx (
b0 '
0&
b0 %
b0 $
b0 #
0"
bx !
$end
#10
1"
#20
0"
#30
1"
b1010000 #
b1010000 '
b1010000 $
b1010000 )
b1010000 %
b1010000 *
1&
#40
0"
#50
b1010000 !
b1010000 (
b1010000 +
1"
b1011010 %
b1011010 *
b0 $
b0 )
#60
0"
#70
1"
b1010000 $
b1010000 )
#80
0"
#90
b1011010 !
b1011010 (
b1011010 +
1"
b0 #
b0 '
b1111111111 $
b1111111111 )
#100
0"
#110
1"
b1010000 #
b1010000 '
#120
0"
#130
bx !
bx (
bx +
1"
b1111101000 #
b1111101000 '
#140
0"
#150
b1011010 !
b1011010 (
b1011010 +
1"
b1111111111 #
b1111111111 '
