sequential_circuits/jk_flip_flop/jk_flip_flop.v
module jk_flip_flop(q, nq, j, k, clk);
    input j,k,clk;
    output reg q,nq;
    integer i;
    always @(posedge clk) begin
        i = {j, k};
        case (i)
            2'b00: begin
                q <= q; nq <= nq;
            end
            2'b01: begin
                q <= 0; nq <= 1;
            end
            2'b10: begin
                q <= 1; nq <= 0;
            end
            2'b11: begin 
                q <= nq; nq <= q;
            end
        endcase
    end
endmodule

sequential_circuits/jk_flip_flop/jk_flip_flop_tb.v
`timescale 1ps/1ps
`include "jk_flip_flop.v"

module jk_flip_flop_tb;
    reg j, k, clk;
    wire q, nq;
    integer i;
    jk_flip_flop jkff1(q, nq, j, k, clk);
    initial begin
        clk = 0;
        for (i = 0; i < 5000; i = i + 1) begin
            #10 clk = ~clk;
        end
    end
    initial begin
        $dumpfile("jk_flip_flop_tb.vcd");
        $dumpvars;
        j = 1; k = 0;
        #100 j = 0; k = 0;
        #100 j = 0; k = 1;
        #100 j = 0; k = 0;
        #100 j = 1; k = 1;
        #500 j = 0; k = 0;
    end
endmodule

sequential_circuits/jk_flip_flop/jk_flip_flop_tb.vcd
$date
	Sat Dec 30 16:50:45 2023
$end
$version
	Icarus Verilog
$end
$timescale
	1ps
$end
$scope module jk_flip_flop_tb $end
$var wire 1 ! q $end
$var wire 1 " nq $end
$var reg 1 # clk $end
$var reg 1 $ j $end
$var reg 1 % k $end
$var integer 32 & i [31:0] $end
$scope module jkff1 $end
$var wire 1 # clk $end
$var wire 1 $ j $end
$var wire 1 % k $end
$var reg 1 " nq $end
$var reg 1 ! q $end
$var integer 32 ' i [31:0] $end
$upscope $end
$upscope $end
$enddefinitions $end
$comment Show the parameter values. $end
$dumpall
$end
#0
$dumpvars
bx '
b0 &
0%
1$
0#
x"
x!
$end
#10
0"
1!
b10 '
b1 &
1#
#20
b10 &
0#
#30
b11 &
1#
#40
b100 &
0#
#50
b101 &
1#
#60
b110 &
0#
#70
b111 &
1#
#80
b1000 &
0#
#90
b1001 &
1#
#100
b1010 &
0#
0$
#110
b0 '
b1011 &
1#
#120
b1100 &
0#
#130
b1101 &
1#
#140
b1110 &
0#
#150
b1111 &
1#
#160
b10000 &
0#
#170
b10001 &
1#
#180
b10010 &
0#
#190
b10011 &
1#
#200
b10100 &
0#
1%
#210
1"
0!
b1 '
b10101 &
1#
#220
b10110 &
0#
#230
b10111 &
1#
#240
b11000 &
0#
#250
b11001 &
1#
#260
b11010 &
0#
#270
b11011 &
1#
#280
b11100 &
0#
#290
b11101 &
1#
#300
b11110 &
0#
0%
#310
b0 '
b11111 &
1#
#320
b100000 &
0#
#330
b100001 &
1#
#340
b100010 &
0#
#350
b100011 &
1#
#360
b100100 &
0#
#370
b100101 &
1#
#380
b100110 &
0#
#390
b100111 &
1#
#400
b101000 &
0#
1%
1$
#410
0"
1!
b11 '
b101001 &
1#
#420
b101010 &
0#
#430
1"
0!
b101011 &
1#
#440
b101100 &
0#
#450
0"
1!
b101101 &
1#
#460
b101110 &
0#
#470
1"
0!
b101111 &
1#
#480
b110000 &
0#
#490
0"
1!
b110001 &
1#
#500
b110010 &
0#
#510
1"
0!
b110011 &
1#
#520
b110100 &
0#
#530
0"
1!
b110101 &
1#
#540
b110110 &
0#
#550
1"
0!
b110111 &
1#
#560
b111000 &
0#
#570
0"
1!
b111001 &
1#
#580
b111010 &
0#
#590
1"
0!
b111011 &
1#
#600
b111100 &
0#
#610
0"
1!
b111101 &
1#
#620
b111110 &
0#
#630
1"
0!
b111111 &
1#
#640
b1000000 &
0#
#650
0"
1!
b1000001 &
1#
#660
b1000010 &
0#
#670
1"
0!
b1000011 &
1#
#680
b1000100 &
0#
#690
0"
1!
b1000101 &
1#
#700
b1000110 &
0#
#710
1"
0!
b1000111 &
1#
#720
b1001000 &
0#
#730
0"
1!
b1001001 &
1#
#740
b1001010 &
0#
#750
1"
0!
b1001011 &
1#
#760
b1001100 &
0#
#770
0"
1!
b1001101 &
1#
#780
b1001110 &
0#
#790
1"
0!
b1001111 &
1#
#800
b1010000 &
0#
#810
0"
1!
b1010001 &
1#
#820
b1010010 &
0#
#830
1"
0!
b1010011 &
1#
#840
b1010100 &
0#
#850
0"
1!
b1010101 &
1#
#860
b1010110 &
0#
#870
1"
0!
b1010111 &
1#
#880
b1011000 &
0#
#890
0"
1!
b1011001 &
1#
#900
b1011010 &
0#
0%
0$
#910
b0 '
b1011011 &
1#
#920
b1011100 &
0#
#930
b1011101 &
1#
#940
b1011110 &
0#
#950
b1011111 &
1#
#960
b1100000 &
0#
#970
b1100001 &
1#
#980
b1100010 &
0#
#990
b1100011 &
1#
#1000
b1100100 &
0#
#1010
b1100101 &
1#
#1020
b1100110 &
0#
#1030
b1100111 &
1#
#1040
b1101000 &
0#
#1050
b1101001 &
1#
#1060
b1101010 &
0#
#1070
b1101011 &
1#
#1080
b1101100 &
0#
#1090
b1101101 &
1#
#1100
b1101110 &
0#
#1110
b1101111 &
1#
#1120
b1110000 &
0#
#1130
b1110001 &
1#
#1140
b1110010 &
0#
#1150
b1110011 &
1#
#1160
b1110100 &
0#
#1170
b1110101 &
1#
#1180
b1110110 &
0#
#1190
b1110111 &
1#
#1200
b1111000 &
0#
#1210
b1111001 &
1#
#1220
b1111010 &
0#
#1230
b1111011 &
1#
#1240
b1111100 &
0#
#1250
b1111101 &
1#
#1260
b1111110 &
0#
#1270
b1111111 &
1#
#1280
b10000000 &
0#
#1290
b10000001 &
1#
#1300
b10000010 &
0#
#1310
b10000011 &
1#
#1320
b10000100 &
0#
#1330
b10000101 &
1#
#1340
b10000110 &
0#
#1350
b10000111 &
1#
#1360
b10001000 &
0#
#1370
b10001001 &
1#
#1380
b10001010 &
0#
#1390
b10001011 &
1#
#1400
b10001100 &
0#
#1410
b10001101 &
1#
#1420
b10001110 &
0#
#1430
b10001111 &
1#
#1440
b10010000 &
0#
#1450
b10010001 &
1#
#1460
b10010010 &
0#
#1470
b10010011 &
1#
#1480
b10010100 &
0#
#1490
b10010101 &
1#
#1500
b10010110 &
0#
#1510
b10010111 &
1#
#1520
b10011000 &
0#
#1530
b10011001 &
1#
#1540
b10011010 &
0#
#1550
b10011011 &
1#
#1560
b10011100 &
0#
#1570
b10011101 &
1#
#1580
b10011110 &
0#
#1590
b10011111 &
1#
#1600
b10100000 &
0#
#1610
b10100001 &
1#
#1620
b10100010 &
0#
#1630
b10100011 &
1#
#1640
b10100100 &
0#
#1650
b10100101 &
1#
#1660
b10100110 &
0#
#1670
b10100111 &
1#
#1680
b10101000 &
0#
#1690
b10101001 &
1#
#1700
b10101010 &
0#
#1710
b10101011 &
1#
#1720
b10101100 &
0#
#1730
b10101101 &
1#
#1740
b10101110 &
0#
#1750
b10101111 &
1#
#1760
b10110000 &
0#
#1770
b10110001 &
1#
#1780
b10110010 &
0#
#1790
b10110011 &
1#
#1800
b10110100 &
0#
#1810
b10110101 &
1#
#1820
b10110110 &
0#
#1830
b10110111 &
1#
#1840
b10111000 &
0#
#1850
b10111001 &
1#
#1860
b10111010 &
0#
#1870
b10111011 &
1#
#1880
b10111100 &
0#
#1890
b10111101 &
1#
#1900
b10111110 &
0#
#1910
b10111111 &
1#
#1920
b11000000 &
0#
#1930
b11000001 &
1#
#1940
b11000010 &
0#
#1950
b11000011 &
1#
#1960
b11000100 &
0#
#1970
b11000101 &
1#
#1980
b11000110 &
0#
#1990
b11000111 &
1#
#2000
b11001000 &
0#
#2010
b11001001 &
1#
#2020
b11001010 &
0#
#2030
b11001011 &
1#
#2040
b11001100 &
0#
#2050
b11001101 &
1#
#2060
b11001110 &
0#
#2070
b11001111 &
1#
#2080
b11010000 &
0#
#2090
b11010001 &
1#
#2100
b11010010 &
0#
#2110
b11010011 &
1#
#2120
b11010100 &
0#
#2130
b11010101 &
1#
#2140
b11010110 &
0#
#2150
b11010111 &
1#
#2160
b11011000 &
0#
#2170
b11011001 &
1#
#2180
b11011010 &
0#
#2190
b11011011 &
1#
#2200
b11011100 &
0#
#2210
b11011101 &
1#
#2220
b11011110 &
0#
#2230
b11011111 &
1#
#2240
b11100000 &
0#
#2250
b11100001 &
1#
#2260
b11100010 &
0#
#2270
b11100011 &
1#
#2280
b11100100 &
0#
#2290
b11100101 &
1#
#2300
b11100110 &
0#
#2310
b11100111 &
1#
#2320
b11101000 &
0#
#2330
b11101001 &
1#
#2340
b11101010 &
0#
#2350
b11101011 &
1#
#2360
b11101100 &
0#
#2370
b11101101 &
1#
#2380
b11101110 &
0#
#2390
b11101111 &
1#
#2400
b11110000 &
0#
#2410
b11110001 &
1#
#2420
b11110010 &
0#
#2430
b11110011 &
1#
#2440
b11110100 &
0#
#2450
b11110101 &
1#
#2460
b11110110 &
0#
#2470
b11110111 &
1#
#2480
b11111000 &
0#
#2490
b11111001 &
1#
#2500
b11111010 &
0#
#2510
b11111011 &
1#
#2520
b11111100 &
0#
#2530
b11111101 &
1#
#2540
b11111110 &
0#
#2550
b11111111 &
1#
#2560
b100000000 &
0#
#2570
b100000001 &
1#
#2580
b100000010 &
0#
#2590
b100000011 &
1#
#2600
b100000100 &
0#
#2610
b100000101 &
1#
#2620
b100000110 &
0#
#2630
b100000111 &
1#
#2640
b100001000 &
0#
#2650
b100001001 &
1#
#2660
b100001010 &
0#
#2670
b100001011 &
1#
#2680
b100001100 &
0#
#2690
b100001101 &
1#
#2700
b100001110 &
0#
#2710
b100001111 &
1#
#2720
b100010000 &
0#
#2730
b100010001 &
1#
#2740
b100010010 &
0#
#2750
b100010011 &
1#
#2760
b100010100 &
0#
#2770
b100010101 &
1#
#2780
b100010110 &
0#
#2790
b100010111 &
1#
#2800
b100011000 &
0#
#2810
b100011001 &
1#
#2820
b100011010 &
0#
#2830
b100011011 &
1#
#2840
b100011100 &
0#
#2850
b100011101 &
1#
#2860
b100011110 &
0#
#2870
b100011111 &
1#
#2880
b100100000 &
0#
#2890
b100100001 &
1#
#2900
b100100010 &
0#
#2910
b100100011 &
1#
#2920
b100100100 &
0#
#2930
b100100101 &
1#
#2940
b100100110 &
0#
#2950
b100100111 &
1#
#2960
b100101000 &
0#
#2970
b100101001 &
1#
#2980
b100101010 &
0#
#2990
b100101011 &
1#
#3000
b100101100 &
0#
#3010
b100101101 &
1#
#3020
b100101110 &
0#
#3030
b100101111 &
1#
#3040
b100110000 &
0#
#3050
b100110001 &
1#
#3060
b100110010 &
0#
#3070
b100110011 &
1#
#3080
b100110100 &
0#
#3090
b100110101 &
1#
#3100
b100110110 &
0#
#3110
b100110111 &
1#
#3120
b100111000 &
0#
#3130
b100111001 &
1#
#3140
b100111010 &
0#
#3150
b100111011 &
1#
#3160
b100111100 &
0#
#3170
b100111101 &
1#
#3180
b100111110 &
0#
#3190
b100111111 &
1#
#3200
b101000000 &
0#
#3210
b101000001 &
1#
#3220
b101000010 &
0#
#3230
b101000011 &
1#
#3240
b101000100 &
0#
#3250
b101000101 &
1#
#3260
b101000110 &
0#
#3270
b101000111 &
1#
#3280
b101001000 &
0#
#3290
b101001001 &
1#
#3300
b101001010 &
0#
#3310
b101001011 &
1#
#3320
b101001100 &
0#
#3330
b101001101 &
1#
#3340
b101001110 &
0#
#3350
b101001111 &
1#
#3360
b101010000 &
0#
#3370
b101010001 &
1#
#3380
b101010010 &
0#
#3390
b101010011 &
1#
#3400
b101010100 &
0#
#3410
b101010101 &
1#
#3420
b101010110 &
0#
#3430
b101010111 &
1#
#3440
b101011000 &
0#
#3450
b101011001 &
1#
#3460
b101011010 &
0#
#3470
b101011011 &
1#
#3480
b101011100 &
0#
#3490
b101011101 &
1#
#3500
b101011110 &
0#
#3510
b101011111 &
1#
#3520
b101100000 &
0#
#3530
b101100001 &
1#
#3540
b101100010 &
0#
#3550
b101100011 &
1#
#3560
b101100100 &
0#
#3570
b101100101 &
1#
#3580
b101100110 &
0#
#3590
b101100111 &
1#
#3600
b101101000 &
0#
#3610
b101101001 &
1#
#3620
b101101010 &
0#
#3630
b101101011 &
1#
#3640
b101101100 &
0#
#3650
b101101101 &
1#
#3660
b101101110 &
0#
#3670
b101101111 &
1#
#3680
b101110000 &
0#
#3690
b101110001 &
1#
#3700
b101110010 &
0#
#3710
b101110011 &
1#
#3720
b101110100 &
0#
#3730
b101110101 &
1#
#3740
b101110110 &
0#
#3750
b101110111 &
1#
#3760
b101111000 &
0#
#3770
b101111001 &
1#
#3780
b101111010 &
0#
#3790
b101111011 &
1#
#3800
b101111100 &
0#
#3810
b101111101 &
1#
#3820
b101111110 &
0#
#3830
b101111111 &
1#
#3840
b110000000 &
0#
#3850
b110000001 &
1#
#3860
b110000010 &
0#
#3870
b110000011 &
1#
#3880
b110000100 &
0#
#3890
b110000101 &
1#
#3900
b110000110 &
0#
#3910
b110000111 &
1#
#3920
b110001000 &
0#
#3930
b110001001 &
1#
#3940
b110001010 &
0#
#3950
b110001011 &
1#
#3960
b110001100 &
0#
#3970
b110001101 &
1#
#3980
b110001110 &
0#
#3990
b110001111 &
1#
#4000
b110010000 &
0#
#4010
b110010001 &
1#
#4020
b110010010 &
0#
#4030
b110010011 &
1#
#4040
b110010100 &
0#
#4050
b110010101 &
1#
#4060
b110010110 &
0#
#4070
b110010111 &
1#
#4080
b110011000 &
0#
#4090
b110011001 &
1#
#4100
b110011010 &
0#
#4110
b110011011 &
1#
#4120
b110011100 &
0#
#4130
b110011101 &
1#
#4140
b110011110 &
0#
#4150
b110011111 &
1#
#4160
b110100000 &
0#
#4170
b110100001 &
1#
#4180
b110100010 &
0#
#4190
b110100011 &
1#
#4200
b110100100 &
0#
#4210
b110100101 &
1#
#4220
b110100110 &
0#
#4230
b110100111 &
1#
#4240
b110101000 &
0#
#4250
b110101001 &
1#
#4260
b110101010 &
0#
#4270
b110101011 &
1#
#4280
b110101100 &
0#
#4290
b110101101 &
1#
#4300
b110101110 &
0#
#4310
b110101111 &
1#
#4320
b110110000 &
0#
#4330
b110110001 &
1#
#4340
b110110010 &
0#
#4350
b110110011 &
1#
#4360
b110110100 &
0#
#4370
b110110101 &
1#
#4380
b110110110 &
0#
#4390
b110110111 &
1#
#4400
b110111000 &
0#
#4410
b110111001 &
1#
#4420
b110111010 &
0#
#4430
b110111011 &
1#
#4440
b110111100 &
0#
#4450
b110111101 &
1#
#4460
b110111110 &
0#
#4470
b110111111 &
1#
#4480
b111000000 &
0#
#4490
b111000001 &
1#
#4500
b111000010 &
0#
#4510
b111000011 &
1#
#4520
b111000100 &
0#
#4530
b111000101 &
1#
#4540
b111000110 &
0#
#4550
b111000111 &
1#
#4560
b111001000 &
0#
#4570
b111001001 &
1#
#4580
b111001010 &
0#
#4590
b111001011 &
1#
#4600
b111001100 &
0#
#4610
b111001101 &
1#
#4620
b111001110 &
0#
#4630
b111001111 &
1#
#4640
b111010000 &
0#
#4650
b111010001 &
1#
#4660
b111010010 &
0#
#4670
b111010011 &
1#
#4680
b111010100 &
0#
#4690
b111010101 &
1#
#4700
b111010110 &
0#
#4710
b111010111 &
1#
#4720
b111011000 &
0#
#4730
b111011001 &
1#
#4740
b111011010 &
0#
#4750
b111011011 &
1#
#4760
b111011100 &
0#
#4770
b111011101 &
1#
#4780
b111011110 &
0#
#4790
b111011111 &
1#
#4800
b111100000 &
0#
#4810
b111100001 &
1#
#4820
b111100010 &
0#
#4830
b111100011 &
1#
#4840
b111100100 &
0#
#4850
b111100101 &
1#
#4860
b111100110 &
0#
#4870
b111100111 &
1#
#4880
b111101000 &
0#
#4890
b111101001 &
1#
#4900
b111101010 &
0#
#4910
b111101011 &
1#
#4920
b111101100 &
0#
#4930
b111101101 &
1#
#4940
b111101110 &
0#
#4950
b111101111 &
1#
#4960
b111110000 &
0#
#4970
b111110001 &
1#
#4980
b111110010 &
0#
#4990
b111110011 &
1#
#5000
b111110100 &
0#
#5010
b111110101 &
1#
#5020
b111110110 &
0#
#5030
b111110111 &
1#
#5040
b111111000 &
0#
#5050
b111111001 &
1#
#5060
b111111010 &
0#
#5070
b111111011 &
1#
#5080
b111111100 &
0#
#5090
b111111101 &
1#
#5100
b111111110 &
0#
#5110
b111111111 &
1#
#5120
b1000000000 &
0#
#5130
b1000000001 &
1#
#5140
b1000000010 &
0#
#5150
b1000000011 &
1#
#5160
b1000000100 &
0#
#5170
b1000000101 &
1#
#5180
b1000000110 &
0#
#5190
b1000000111 &
1#
#5200
b1000001000 &
0#
#5210
b1000001001 &
1#
#5220
b1000001010 &
0#
#5230
b1000001011 &
1#
#5240
b1000001100 &
0#
#5250
b1000001101 &
1#
#5260
b1000001110 &
0#
#5270
b1000001111 &
1#
#5280
b1000010000 &
0#
#5290
b1000010001 &
1#
#5300
b1000010010 &
0#
#5310
b1000010011 &
1#
#5320
b1000010100 &
0#
#5330
b1000010101 &
1#
#5340
b1000010110 &
0#
#5350
b1000010111 &
1#
#5360
b1000011000 &
0#
#5370
b1000011001 &
1#
#5380
b1000011010 &
0#
#5390
b1000011011 &
1#
#5400
b1000011100 &
0#
#5410
b1000011101 &
1#
#5420
b1000011110 &
0#
#5430
b1000011111 &
1#
#5440
b1000100000 &
0#
#5450
b1000100001 &
1#
#5460
b1000100010 &
0#
#5470
b1000100011 &
1#
#5480
b1000100100 &
0#
#5490
b1000100101 &
1#
#5500
b1000100110 &
0#
#5510
b1000100111 &
1#
#5520
b1000101000 &
0#
#5530
b1000101001 &
1#
#5540
b1000101010 &
0#
#5550
b1000101011 &
1#
#5560
b1000101100 &
0#
#5570
b1000101101 &
1#
#5580
b1000101110 &
0#
#5590
b1000101111 &
1#
#5600
b1000110000 &
0#
#5610
b1000110001 &
1#
#5620
b1000110010 &
0#
#5630
b1000110011 &
1#
#5640
b1000110100 &
0#
#5650
b1000110101 &
1#
#5660
b1000110110 &
0#
#5670
b1000110111 &
1#
#5680
b1000111000 &
0#
#5690
b1000111001 &
1#
#5700
b1000111010 &
0#
#5710
b1000111011 &
1#
#5720
b1000111100 &
0#
#5730
b1000111101 &
1#
#5740
b1000111110 &
0#
#5750
b1000111111 &
1#
#5760
b1001000000 &
0#
#5770
b1001000001 &
1#
#5780
b1001000010 &
0#
#5790
b1001000011 &
1#
#5800
b1001000100 &
0#
#5810
b1001000101 &
1#
#5820
b1001000110 &
0#
#5830
b1001000111 &
1#
#5840
b1001001000 &
0#
#5850
b1001001001 &
1#
#5860
b1001001010 &
0#
#5870
b1001001011 &
1#
#5880
b1001001100 &
0#
#5890
b1001001101 &
1#
#5900
b1001001110 &
0#
#5910
b1001001111 &
1#
#5920
b1001010000 &
0#
#5930
b1001010001 &
1#
#5940
b1001010010 &
0#
#5950
b1001010011 &
1#
#5960
b1001010100 &
0#
#5970
b1001010101 &
1#
#5980
b1001010110 &
0#
#5990
b1001010111 &
1#
#6000
b1001011000 &
0#
#6010
b1001011001 &
1#
#6020
b1001011010 &
0#
#6030
b1001011011 &
1#
#6040
b1001011100 &
0#
#6050
b1001011101 &
1#
#6060
b1001011110 &
0#
#6070
b1001011111 &
1#
#6080
b1001100000 &
0#
#6090
b1001100001 &
1#
#6100
b1001100010 &
0#
#6110
b1001100011 &
1#
#6120
b1001100100 &
0#
#6130
b1001100101 &
1#
#6140
b1001100110 &
0#
#6150
b1001100111 &
1#
#6160
b1001101000 &
0#
#6170
b1001101001 &
1#
#6180
b1001101010 &
0#
#6190
b1001101011 &
1#
#6200
b1001101100 &
0#
#6210
b1001101101 &
1#
#6220
b1001101110 &
0#
#6230
b1001101111 &
1#
#6240
b1001110000 &
0#
#6250
b1001110001 &
1#
#6260
b1001110010 &
0#
#6270
b1001110011 &
1#
#6280
b1001110100 &
0#
#6290
b1001110101 &
1#
#6300
b1001110110 &
0#
#6310
b1001110111 &
1#
#6320
b1001111000 &
0#
#6330
b1001111001 &
1#
#6340
b1001111010 &
0#
#6350
b1001111011 &
1#
#6360
b1001111100 &
0#
#6370
b1001111101 &
1#
#6380
b1001111110 &
0#
#6390
b1001111111 &
1#
#6400
b1010000000 &
0#
#6410
b1010000001 &
1#
#6420
b1010000010 &
0#
#6430
b1010000011 &
1#
#6440
b1010000100 &
0#
#6450
b1010000101 &
1#
#6460
b1010000110 &
0#
#6470
b1010000111 &
1#
#6480
b1010001000 &
0#
#6490
b1010001001 &
1#
#6500
b1010001010 &
0#
#6510
b1010001011 &
1#
#6520
b1010001100 &
0#
#6530
b1010001101 &
1#
#6540
b1010001110 &
0#
#6550
b1010001111 &
1#
#6560
b1010010000 &
0#
#6570
b1010010001 &
1#
#6580
b1010010010 &
0#
#6590
b1010010011 &
1#
#6600
b1010010100 &
0#
#6610
b1010010101 &
1#
#6620
b1010010110 &
0#
#6630
b1010010111 &
1#
#6640
b1010011000 &
0#
#6650
b1010011001 &
1#
#6660
b1010011010 &
0#
#6670
b1010011011 &
1#
#6680
b1010011100 &
0#
#6690
b1010011101 &
1#
#6700
b1010011110 &
0#
#6710
b1010011111 &
1#
#6720
b1010100000 &
0#
#6730
b1010100001 &
1#
#6740
b1010100010 &
0#
#6750
b1010100011 &
1#
#6760
b1010100100 &
0#
#6770
b1010100101 &
1#
#6780
b1010100110 &
0#
#6790
b1010100111 &
1#
#6800
b1010101000 &
0#
#6810
b1010101001 &
1#
#6820
b1010101010 &
0#
#6830
b1010101011 &
1#
#6840
b1010101100 &
0#
#6850
b1010101101 &
1#
#6860
b1010101110 &
0#
#6870
b1010101111 &
1#
#6880
b1010110000 &
0#
#6890
b1010110001 &
1#
#6900
b1010110010 &
0#
#6910
b1010110011 &
1#
#6920
b1010110100 &
0#
#6930
b1010110101 &
1#
#6940
b1010110110 &
0#
#6950
b1010110111 &
1#
#6960
b1010111000 &
0#
#6970
b1010111001 &
1#
#6980
b1010111010 &
0#
#6990
b1010111011 &
1#
#7000
b1010111100 &
0#
#7010
b1010111101 &
1#
#7020
b1010111110 &
0#
#7030
b1010111111 &
1#
#7040
b1011000000 &
0#
#7050
b1011000001 &
1#
#7060
b1011000010 &
0#
#7070
b1011000011 &
1#
#7080
b1011000100 &
0#
#7090
b1011000101 &
1#
#7100
b1011000110 &
0#
#7110
b1011000111 &
1#
#7120
b1011001000 &
0#
#7130
b1011001001 &
1#
#7140
b1011001010 &
0#
#7150
b1011001011 &
1#
#7160
b1011001100 &
0#
#7170
b1011001101 &
1#
#7180
b1011001110 &
0#
#7190
b1011001111 &
1#
#7200
b1011010000 &
0#
#7210
b1011010001 &
1#
#7220
b1011010010 &
0#
#7230
b1011010011 &
1#
#7240
b1011010100 &
0#
#7250
b1011010101 &
1#
#7260
b1011010110 &
0#
#7270
b1011010111 &
1#
#7280
b1011011000 &
0#
#7290
b1011011001 &
1#
#7300
b1011011010 &
0#
#7310
b1011011011 &
1#
#7320
b1011011100 &
0#
#7330
b1011011101 &
1#
#7340
b1011011110 &
0#
#7350
b1011011111 &
1#
#7360
b1011100000 &
0#
#7370
b1011100001 &
1#
#7380
b1011100010 &
0#
#7390
b1011100011 &
1#
#7400
b1011100100 &
0#
#7410
b1011100101 &
1#
#7420
b1011100110 &
0#
#7430
b1011100111 &
1#
#7440
b1011101000 &
0#
#7450
b1011101001 &
1#
#7460
b1011101010 &
0#
#7470
b1011101011 &
1#
#7480
b1011101100 &
0#
#7490
b1011101101 &
1#
#7500
b1011101110 &
0#
#7510
b1011101111 &
1#
#7520
b1011110000 &
0#
#7530
b1011110001 &
1#
#7540
b1011110010 &
0#
#7550
b1011110011 &
1#
#7560
b1011110100 &
0#
#7570
b1011110101 &
1#
#7580
b1011110110 &
0#
#7590
b1011110111 &
1#
#7600
b1011111000 &
0#
#7610
b1011111001 &
1#
#7620
b1011111010 &
0#
#7630
b1011111011 &
1#
#7640
b1011111100 &
0#
#7650
b1011111101 &
1#
#7660
b1011111110 &
0#
#7670
b1011111111 &
1#
#7680
b1100000000 &
0#
#7690
b1100000001 &
1#
#7700
b1100000010 &
0#
#7710
b1100000011 &
1#
#7720
b1100000100 &
0#
#7730
b1100000101 &
1#
#7740
b1100000110 &
0#
#7750
b1100000111 &
1#
#7760
b1100001000 &
0#
#7770
b1100001001 &
1#
#7780
b1100001010 &
0#
#7790
b1100001011 &
1#
#7800
b1100001100 &
0#
#7810
b1100001101 &
1#
#7820
b1100001110 &
0#
#7830
b1100001111 &
1#
#7840
b1100010000 &
0#
#7850
b1100010001 &
1#
#7860
b1100010010 &
0#
#7870
b1100010011 &
1#
#7880
b1100010100 &
0#
#7890
b1100010101 &
1#
#7900
b1100010110 &
0#
#7910
b1100010111 &
1#
#7920
b1100011000 &
0#
#7930
b1100011001 &
1#
#7940
b1100011010 &
0#
#7950
b1100011011 &
1#
#7960
b1100011100 &
0#
#7970
b1100011101 &
1#
#7980
b1100011110 &
0#
#7990
b1100011111 &
1#
#8000
b1100100000 &
0#
#8010
b1100100001 &
1#
#8020
b1100100010 &
0#
#8030
b1100100011 &
1#
#8040
b1100100100 &
0#
#8050
b1100100101 &
1#
#8060
b1100100110 &
0#
#8070
b1100100111 &
1#
#8080
b1100101000 &
0#
#8090
b1100101001 &
1#
#8100
b1100101010 &
0#
#8110
b1100101011 &
1#
#8120
b1100101100 &
0#
#8130
b1100101101 &
1#
#8140
b1100101110 &
0#
#8150
b1100101111 &
1#
#8160
b1100110000 &
0#
#8170
b1100110001 &
1#
#8180
b1100110010 &
0#
#8190
b1100110011 &
1#
#8200
b1100110100 &
0#
#8210
b1100110101 &
1#
#8220
b1100110110 &
0#
#8230
b1100110111 &
1#
#8240
b1100111000 &
0#
#8250
b1100111001 &
1#
#8260
b1100111010 &
0#
#8270
b1100111011 &
1#
#8280
b1100111100 &
0#
#8290
b1100111101 &
1#
#8300
b1100111110 &
0#
#8310
b1100111111 &
1#
#8320
b1101000000 &
0#
#8330
b1101000001 &
1#
#8340
b1101000010 &
0#
#8350
b1101000011 &
1#
#8360
b1101000100 &
0#
#8370
b1101000101 &
1#
#8380
b1101000110 &
0#
#8390
b1101000111 &
1#
#8400
b1101001000 &
0#
#8410
b1101001001 &
1#
#8420
b1101001010 &
0#
#8430
b1101001011 &
1#
#8440
b1101001100 &
0#
#8450
b1101001101 &
1#
#8460
b1101001110 &
0#
#8470
b1101001111 &
1#
#8480
b1101010000 &
0#
#8490
b1101010001 &
1#
#8500
b1101010010 &
0#
#8510
b1101010011 &
1#
#8520
b1101010100 &
0#
#8530
b1101010101 &
1#
#8540
b1101010110 &
0#
#8550
b1101010111 &
1#
#8560
b1101011000 &
0#
#8570
b1101011001 &
1#
#8580
b1101011010 &
0#
#8590
b1101011011 &
1#
#8600
b1101011100 &
0#
#8610
b1101011101 &
1#
#8620
b1101011110 &
0#
#8630
b1101011111 &
1#
#8640
b1101100000 &
0#
#8650
b1101100001 &
1#
#8660
b1101100010 &
0#
#8670
b1101100011 &
1#
#8680
b1101100100 &
0#
#8690
b1101100101 &
1#
#8700
b1101100110 &
0#
#8710
b1101100111 &
1#
#8720
b1101101000 &
0#
#8730
b1101101001 &
1#
#8740
b1101101010 &
0#
#8750
b1101101011 &
1#
#8760
b1101101100 &
0#
#8770
b1101101101 &
1#
#8780
b1101101110 &
0#
#8790
b1101101111 &
1#
#8800
b1101110000 &
0#
#8810
b1101110001 &
1#
#8820
b1101110010 &
0#
#8830
b1101110011 &
1#
#8840
b1101110100 &
0#
#8850
b1101110101 &
1#
#8860
b1101110110 &
0#
#8870
b1101110111 &
1#
#8880
b1101111000 &
0#
#8890
b1101111001 &
1#
#8900
b1101111010 &
0#
#8910
b1101111011 &
1#
#8920
b1101111100 &
0#
#8930
b1101111101 &
1#
#8940
b1101111110 &
0#
#8950
b1101111111 &
1#
#8960
b1110000000 &
0#
#8970
b1110000001 &
1#
#8980
b1110000010 &
0#
#8990
b1110000011 &
1#
#9000
b1110000100 &
0#
#9010
b1110000101 &
1#
#9020
b1110000110 &
0#
#9030
b1110000111 &
1#
#9040
b1110001000 &
0#
#9050
b1110001001 &
1#
#9060
b1110001010 &
0#
#9070
b1110001011 &
1#
#9080
b1110001100 &
0#
#9090
b1110001101 &
1#
#9100
b1110001110 &
0#
#9110
b1110001111 &
1#
#9120
b1110010000 &
0#
#9130
b1110010001 &
1#
#9140
b1110010010 &
0#
#9150
b1110010011 &
1#
#9160
b1110010100 &
0#
#9170
b1110010101 &
1#
#9180
b1110010110 &
0#
#9190
b1110010111 &
1#
#9200
b1110011000 &
0#
#9210
b1110011001 &
1#
#9220
b1110011010 &
0#
#9230
b1110011011 &
1#
#9240
b1110011100 &
0#
#9250
b1110011101 &
1#
#9260
b1110011110 &
0#
#9270
b1110011111 &
1#
#9280
b1110100000 &
0#
#9290
b1110100001 &
1#
#9300
b1110100010 &
0#
#9310
b1110100011 &
1#
#9320
b1110100100 &
0#
#9330
b1110100101 &
1#
#9340
b1110100110 &
0#
#9350
b1110100111 &
1#
#9360
b1110101000 &
0#
#9370
b1110101001 &
1#
#9380
b1110101010 &
0#
#9390
b1110101011 &
1#
#9400
b1110101100 &
0#
#9410
b1110101101 &
1#
#9420
b1110101110 &
0#
#9430
b1110101111 &
1#
#9440
b1110110000 &
0#
#9450
b1110110001 &
1#
#9460
b1110110010 &
0#
#9470
b1110110011 &
1#
#9480
b1110110100 &
0#
#9490
b1110110101 &
1#
#9500
b1110110110 &
0#
#9510
b1110110111 &
1#
#9520
b1110111000 &
0#
#9530
b1110111001 &
1#
#9540
b1110111010 &
0#
#9550
b1110111011 &
1#
#9560
b1110111100 &
0#
#9570
b1110111101 &
1#
#9580
b1110111110 &
0#
#9590
b1110111111 &
1#
#9600
b1111000000 &
0#
#9610
b1111000001 &
1#
#9620
b1111000010 &
0#
#9630
b1111000011 &
1#
#9640
b1111000100 &
0#
#9650
b1111000101 &
1#
#9660
b1111000110 &
0#
#9670
b1111000111 &
1#
#9680
b1111001000 &
0#
#9690
b1111001001 &
1#
#9700
b1111001010 &
0#
